{"core":{"items":[{"id":"chaos","name":"Chaos Orb","image":"/gen/image/WzI1LDE0LHsiZiI6IjJESXRlbXMvQ3VycmVuY3kvQ3VycmVuY3lSZXJvbGxSYXJlIiwic2NhbGUiOjF9XQ/46a2347805/CurrencyRerollRare.png","category":"Currency","detailsId":"chaos-orb"},{"id":"divine","name":"Divine Orb","image":"/gen/image/WzI1LDE0LHsiZiI6IjJESXRlbXMvQ3VycmVuY3kvQ3VycmVuY3lNb2RWYWx1ZXMiLCJzY2FsZSI6MX1d/ec48896769/CurrencyModValues.png","category":"Currency","detailsId":"divine-orb"}],"rates":{"divine":0.001672},"primary":"chaos","secondary":"divine"},"lines":[{"id":"runegraft-of-consecration","primaryValue":2.5,"volumePrimaryValue":2.5,"maxVolumeCurrency":"chaos","maxVolumeRate":0.4,"sparkline":{"totalChange":150.0,"data":[212.4,200,342.1,450.0,null,322.7,150.0]}},{"id":"runegraft-of-gemcraft","primaryValue":230.3,"volumePrimaryValue":268.7,"maxVolumeCurrency":"chaos","maxVolumeRate":0.004342,"sparkline":{"totalChange":115.2,"data":[95.48,29.87,23.08,102.1,113.2,76.77,115.2]}},{"id":"runegraft-of-quaffing","primaryValue":4.5,"volumePrimaryValue":3.00,"maxVolumeCurrency":"chaos","maxVolumeRate":0.2222,"sparkline":{"totalChange":50.0,"data":[10.20,-49.14,45.26,16.94,-47.22,-5.59,50.0]}},{"id":"runegraft-of-rallying","primaryValue":9,"volumePrimaryValue":1.50,"maxVolumeCurrency":"chaos","maxVolumeRate":0.1111,"sparkline":{"totalChange":275,"data":[-11.74,44.76,105.1,351.4,423.2,316.7,275]}},{"id":"runegraft-of-restitching","primaryValue":4,"volumePrimaryValue":2.0,"maxVolumeCurrency":"chaos","maxVolumeRate":0.25,"sparkline":{"totalChange":101.6,"data":[113.6,196.9,30.13,14.63,-35.68,null,101.6]}},{"id":"runegraft-of-stability","primaryValue":78,"volumePrimaryValue":13.00,"maxVolumeCurrency":"chaos","maxVolumeRate":0.01282,"sparkline":{"totalChange":-23.78,"data":[-23.17,-54.50,-40.50,-47.99,-42.32,-43.87,-23.78]}},{"id":"runegraft-of-the-agile","primaryValue":2,"volumePrimaryValue":1.67,"maxVolumeCurrency":"chaos","maxVolumeRate":0.5,"sparkline":{"totalChange":-82.14,"data":[-36.76,-32.96,-25.21,-15.18,-61.61,-16.96,-82.14]}},{"id":"runegraft-of-the-imbued","primaryValue":9,"volumePrimaryValue":1.50,"maxVolumeCurrency":"chaos","maxVolumeRate":0.1111,"sparkline":{"totalChange":154.4,"data":[10.23,22.10,122.7,201.4,238.0,211.6,154.4]}},{"id":"runegraft-of-the-jeweller","primaryValue":2,"volumePrimaryValue":1.33,"maxVolumeCurrency":"chaos","maxVolumeRate":0.5,"sparkline":{"totalChange":100,"data":[273.3,200.2,21.88,43.33,150.0,547.6,100]}},{"id":"runegraft-of-the-novamark","primaryValue":1,"volumePrimaryValue":2.83,"maxVolumeCurrency":"chaos","maxVolumeRate":1,"sparkline":{"totalChange":-33.33,"data":[32.99,49.02,-27.78,351.1,93.91,33.33,-33.33]}},{"id":"runegraft-of-the-river","primaryValue":6,"volumePrimaryValue":13.00,"maxVolumeCurrency":"chaos","maxVolumeRate":0.1667,"sparkline":{"totalChange":20,"data":[-19.20,-30.73,12.48,-93.33,-34.06,34.67,20]}},{"id":"runegraft-of-the-sinistral","primaryValue":1,"volumePrimaryValue":0.6667,"maxVolumeCurrency":"chaos","maxVolumeRate":1,"sparkline":{"totalChange":-53.23,"data":[8.60,21.84,109.9,123.8,-14.27,133.4,-53.23]}},{"id":"runegraft-of-the-spellbound","primaryValue":35,"volumePrimaryValue":11.67,"maxVolumeCurrency":"chaos","maxVolumeRate":0.02857,"sparkline":{"totalChange":1650,"data":[71.51,152.1,274.6,234.9,221.2,1358,1650]}},{"id":"runegraft-of-the-witchmark","primaryValue":4,"volumePrimaryValue":2.67,"maxVolumeCurrency":"chaos","maxVolumeRate":0.25,"sparkline":{"totalChange":-28.57,"data":[53.91,18.24,65.33,1.19,-14.43,107.1,-28.57]}},{"id":"runegraft-of-time","primaryValue":27,"volumePrimaryValue":36.00,"maxVolumeCurrency":"chaos","maxVolumeRate":0.03704,"sparkline":{"totalChange":162.0,"data":[-66.96,-46.86,15.16,10.62,218.0,137.0,162.0]}},{"id":"runegraft-of-treachery","primaryValue":13.91,"volumePrimaryValue":122.8,"maxVolumeCurrency":"chaos","maxVolumeRate":0.07191,"sparkline":{"totalChange":6.90,"data":[-15.18,-18.20,1.51,-15.63,7.58,16.76,6.90]}},{"id":"runegraft-of-bellows","primaryValue":2,"volumePrimaryValue":1.33,"maxVolumeCurrency":"chaos","maxVolumeRate":0.5,"sparkline":{"totalChange":0,"data":[59.04,-7.14,70.48,null,-44.44,18.97,0]}},{"id":"runegraft-of-connection","primaryValue":6,"volumePrimaryValue":31.00,"maxVolumeCurrency":"chaos","maxVolumeRate":0.1667,"sparkline":{"totalChange":9.09,"data":[-47.58,-55.17,-14.02,-81.82,5.66,8.61,9.09]}},{"id":"runegraft-of-fury","primaryValue":29,"volumePrimaryValue":4.83,"maxVolumeCurrency":"chaos","maxVolumeRate":0.03448,"sparkline":{"totalChange":132,"data":[0,-86.33,-92,-10.67,-92,-92,132]}},{"id":"runegraft-of-loyalty","primaryValue":1,"volumePrimaryValue":2.33,"maxVolumeCurrency":"chaos","maxVolumeRate":1,"sparkline":{"totalChange":0,"data":[94.06,241.5,0,130.4,42.14,0,0]}},{"id":"runegraft-of-refraction","primaryValue":3,"volumePrimaryValue":1.5,"maxVolumeCurrency":"chaos","maxVolumeRate":0.3333,"sparkline":{"totalChange":11.76,"data":[-1.41,-4.56,49.33,45.00,6.20,36.60,11.76]}},{"id":"runegraft-of-resurgence","primaryValue":5.5,"volumePrimaryValue":5.5,"maxVolumeCurrency":"chaos","maxVolumeRate":0.1818,"sparkline":{"totalChange":47.24,"data":[-32.66,-44.69,81.04,-27.57,12.65,30.51,47.24]}},{"id":"runegraft-of-rotblood","primaryValue":5,"volumePrimaryValue":0.8333,"maxVolumeCurrency":"chaos","maxVolumeRate":0.2,"sparkline":{"totalChange":-92.57,"data":[-14.82,-31.25,-29.86,-57.30,-72.77,-84.41,-92.57]}},{"id":"runegraft-of-suffering","primaryValue":7.33,"volumePrimaryValue":3.67,"maxVolumeCurrency":"chaos","maxVolumeRate":0.1364,"sparkline":{"totalChange":101.3,"data":[0,-40.98,18.12,-10.33,-28.74,74.62,101.3]}},{"id":"runegraft-of-the-bound","primaryValue":14.73,"volumePrimaryValue":27.00,"maxVolumeCurrency":"chaos","maxVolumeRate":0.06790,"sparkline":{"totalChange":74.32,"data":[-21.31,-36.32,64.54,101.2,-9.92,37.11,74.32]}},{"id":"runegraft-of-the-fortress","primaryValue":815.5,"volumePrimaryValue":1495,"maxVolumeCurrency":"divine","maxVolumeRate":0.7333,"sparkline":{"totalChange":-31.10,"data":[3.64,-17.74,-19.03,-4.28,-17.74,-41.37,-31.10]}},{"id":"runegraft-of-the-soulwick","primaryValue":12,"volumePrimaryValue":4.00,"maxVolumeCurrency":"chaos","maxVolumeRate":0.08333,"sparkline":{"totalChange":-97.61,"data":[-35.06,-69.64,-67.37,-77.01,-69.10,-53.89,-97.61]}},{"id":"runegraft-of-the-warp","primaryValue":1510,"volumePrimaryValue":1258,"maxVolumeCurrency":"chaos","maxVolumeRate":0.0006622,"sparkline":{"totalChange":67.69,"data":[-7.83,-22.86,-15.10,5.26,44.44,162.4,67.69]}}],"items":[{"id":"runegraft-of-consecration","name":"Runegraft of Consecration","image":"/gen/image/WzI1LDE0LHsiZiI6IjJESXRlbXMvQ3VycmVuY3kvU2V0dGxlcnMvVmlsbGFnZVJ1bmUzNiIsInNjYWxlIjoxfV0/1e9982bd4b/VillageRune36.png","category":"Runegrafts","detailsId":"runegraft-of-consecration"},{"id":"runegraft-of-gemcraft","name":"Runegraft of Gemcraft","image":"/gen/image/WzI1LDE0LHsiZiI6IjJESXRlbXMvQ3VycmVuY3kvU2V0dGxlcnMvVmlsbGFnZVJ1bmUxNCIsInNjYWxlIjoxfV0/6288329dc0/VillageRune14.png","category":"Runegrafts","detailsId":"runegraft-of-gemcraft"},{"id":"runegraft-of-quaffing","name":"Runegraft of Quaffing","image":"/gen/image/WzI1LDE0LHsiZiI6IjJESXRlbXMvQ3VycmVuY3kvU2V0dGxlcnMvVmlsbGFnZVJ1bmUyMSIsInNjYWxlIjoxfV0/d9dc5f6d05/VillageRune21.png","category":"Runegrafts","detailsId":"runegraft-of-quaffing"},{"id":"runegraft-of-rallying","name":"Runegraft of Rallying","image":"/gen/image/WzI1LDE0LHsiZiI6IjJESXRlbXMvQ3VycmVuY3kvU2V0dGxlcnMvVmlsbGFnZVJ1bmUzNyIsInNjYWxlIjoxfV0/45985fdb24/VillageRune37.png","category":"Runegrafts","detailsId":"runegraft-of-rallying"},{"id":"runegraft-of-restitching","name":"Runegraft of Restitching","image":"/gen/image/WzI1LDE0LHsiZiI6IjJESXRlbXMvQ3VycmVuY3kvU2V0dGxlcnMvVmlsbGFnZVJ1bmUyMiIsInNjYWxlIjoxfV0/84a974b87d/VillageRune22.png","category":"Runegrafts","detailsId":"runegraft-of-restitching"},{"id":"runegraft-of-stability","name":"Runegraft of Stability","image":"/gen/image/WzI1LDE0LHsiZiI6IjJESXRlbXMvQ3VycmVuY3kvU2V0dGxlcnMvVmlsbGFnZVJ1bmUyIiwic2NhbGUiOjF9XQ/c0bfc39082/VillageRune2.png","category":"Runegrafts","detailsId":"runegraft-of-stability"},{"id":"runegraft-of-the-agile","name":"Runegraft of the Agile","image":"/gen/image/WzI1LDE0LHsiZiI6IjJESXRlbXMvQ3VycmVuY3kvU2V0dGxlcnMvVmlsbGFnZVJ1bmUzMiIsInNjYWxlIjoxfV0/20d6340a74/VillageRune32.png","category":"Runegrafts","detailsId":"runegraft-of-the-agile"},{"id":"runegraft-of-the-imbued","name":"Runegraft of the Imbued","image":"/gen/image/WzI1LDE0LHsiZiI6IjJESXRlbXMvQ3VycmVuY3kvU2V0dGxlcnMvVmlsbGFnZVJ1bmUzMCIsInNjYWxlIjoxfV0/63d0c522fb/VillageRune30.png","category":"Runegrafts","detailsId":"runegraft-of-the-imbued"},{"id":"runegraft-of-the-jeweller","name":"Runegraft of the Jeweller","image":"/gen/image/WzI1LDE0LHsiZiI6IjJESXRlbXMvQ3VycmVuY3kvU2V0dGxlcnMvVmlsbGFnZVJ1bmU4Iiwic2NhbGUiOjF9XQ/f5ea7b3aa9/VillageRune8.png","category":"Runegrafts","detailsId":"runegraft-of-the-jeweller"},{"id":"runegraft-of-the-novamark","name":"Runegraft of the Novamark","image":"/gen/image/WzI1LDE0LHsiZiI6IjJESXRlbXMvQ3VycmVuY3kvU2V0dGxlcnMvVmlsbGFnZVJ1bmUyNSIsInNjYWxlIjoxfV0/fb0f9a5935/VillageRune25.png","category":"Runegrafts","detailsId":"runegraft-of-the-novamark"},{"id":"runegraft-of-the-river","name":"Runegraft of the River","image":"/gen/image/WzI1LDE0LHsiZiI6IjJESXRlbXMvQ3VycmVuY3kvU2V0dGxlcnMvVmlsbGFnZVJ1bmU1Iiwic2NhbGUiOjF9XQ/239b52bb4d/VillageRune5.png","category":"Runegrafts","detailsId":"runegraft-of-the-river"},{"id":"runegraft-of-the-sinistral","name":"Runegraft of the Sinistral","image":"/gen/image/WzI1LDE0LHsiZiI6IjJESXRlbXMvQ3VycmVuY3kvU2V0dGxlcnMvVmlsbGFnZVJ1bmU2Iiwic2NhbGUiOjF9XQ/2eed968220/VillageRune6.png","category":"Runegrafts","detailsId":"runegraft-of-the-sinistral"},{"id":"runegraft-of-the-spellbound","name":"Runegraft of the Spellbound","image":"/gen/image/WzI1LDE0LHsiZiI6IjJESXRlbXMvQ3VycmVuY3kvU2V0dGxlcnMvVmlsbGFnZVJ1bmUyNiIsInNjYWxlIjoxfV0/e19a7e066a/VillageRune26.png","category":"Runegrafts","detailsId":"runegraft-of-the-spellbound"},{"id":"runegraft-of-the-witchmark","name":"Runegraft of the Witchmark","image":"/gen/image/WzI1LDE0LHsiZiI6IjJESXRlbXMvQ3VycmVuY3kvU2V0dGxlcnMvVmlsbGFnZVJ1bmUyNCIsInNjYWxlIjoxfV0/b83d8d141d/VillageRune24.png","category":"Runegrafts","detailsId":"runegraft-of-the-witchmark"},{"id":"runegraft-of-time","name":"Runegraft of Time","image":"/gen/image/WzI1LDE0LHsiZiI6IjJESXRlbXMvQ3VycmVuY3kvU2V0dGxlcnMvVmlsbGFnZVJ1bmUxOSIsInNjYWxlIjoxfV0/9c1836484c/VillageRune19.png","category":"Runegrafts","detailsId":"runegraft-of-time"},{"id":"runegraft-of-treachery","name":"Runegraft of Treachery","image":"/gen/image/WzI1LDE0LHsiZiI6IjJESXRlbXMvQ3VycmVuY3kvU2V0dGxlcnMvVmlsbGFnZVJ1bmUyMCIsInNjYWxlIjoxfV0/6f462c33f6/VillageRune20.png","category":"Runegrafts","detailsId":"runegraft-of-treachery"},{"id":"runegraft-of-bellows","name":"Runegraft of Bellows","image":"/gen/image/WzI1LDE0LHsiZiI6IjJESXRlbXMvQ3VycmVuY3kvU2V0dGxlcnMvVmlsbGFnZVJ1bmUxMyIsInNjYWxlIjoxfV0/0cbbd105c0/VillageRune13.png","category":"Runegrafts","detailsId":"runegraft-of-bellows"},{"id":"runegraft-of-connection","name":"Runegraft of Connection","image":"/gen/image/WzI1LDE0LHsiZiI6IjJESXRlbXMvQ3VycmVuY3kvU2V0dGxlcnMvVmlsbGFnZVJ1bmUyOSIsInNjYWxlIjoxfV0/741ebd3bc3/VillageRune29.png","category":"Runegrafts","detailsId":"runegraft-of-connection"},{"id":"runegraft-of-fury","name":"Runegraft of Fury","image":"/gen/image/WzI1LDE0LHsiZiI6IjJESXRlbXMvQ3VycmVuY3kvU2V0dGxlcnMvVmlsbGFnZVJ1bmUzNCIsInNjYWxlIjoxfV0/c453ece978/VillageRune34.png","category":"Runegrafts","detailsId":"runegraft-of-fury"},{"id":"runegraft-of-loyalty","name":"Runegraft of Loyalty","image":"/gen/image/WzI1LDE0LHsiZiI6IjJESXRlbXMvQ3VycmVuY3kvU2V0dGxlcnMvVmlsbGFnZVJ1bmUyMyIsInNjYWxlIjoxfV0/b856c79baa/VillageRune23.png","category":"Runegrafts","detailsId":"runegraft-of-loyalty"},{"id":"runegraft-of-refraction","name":"Runegraft of Refraction","image":"/gen/image/WzI1LDE0LHsiZiI6IjJESXRlbXMvQ3VycmVuY3kvU2V0dGxlcnMvVmlsbGFnZVJ1bmU3Iiwic2NhbGUiOjF9XQ/953733102b/VillageRune7.png","category":"Runegrafts","detailsId":"runegraft-of-refraction"},{"id":"runegraft-of-resurgence","name":"Runegraft of Resurgence","image":"/gen/image/WzI1LDE0LHsiZiI6IjJESXRlbXMvQ3VycmVuY3kvU2V0dGxlcnMvVmlsbGFnZVJ1bmUzMSIsInNjYWxlIjoxfV0/fd0ff25805/VillageRune31.png","category":"Runegrafts","detailsId":"runegraft-of-resurgence"},{"id":"runegraft-of-rotblood","name":"Runegraft of Rotblood","image":"/gen/image/WzI1LDE0LHsiZiI6IjJESXRlbXMvQ3VycmVuY3kvU2V0dGxlcnMvVmlsbGFnZVJ1bmUzMyIsInNjYWxlIjoxfV0/57870db175/VillageRune33.png","category":"Runegrafts","detailsId":"runegraft-of-rotblood"},{"id":"runegraft-of-suffering","name":"Runegraft of Suffering","image":"/gen/image/WzI1LDE0LHsiZiI6IjJESXRlbXMvQ3VycmVuY3kvU2V0dGxlcnMvVmlsbGFnZVJ1bmUyNyIsInNjYWxlIjoxfV0/4095f212ff/VillageRune27.png","category":"Runegrafts","detailsId":"runegraft-of-suffering"},{"id":"runegraft-of-the-bound","name":"Runegraft of the Bound","image":"/gen/image/WzI1LDE0LHsiZiI6IjJESXRlbXMvQ3VycmVuY3kvU2V0dGxlcnMvVmlsbGFnZVJ1bmUzIiwic2NhbGUiOjF9XQ/7e7fa2cc52/VillageRune3.png","category":"Runegrafts","detailsId":"runegraft-of-the-bound"},{"id":"runegraft-of-the-fortress","name":"Runegraft of the Fortress","image":"/gen/image/WzI1LDE0LHsiZiI6IjJESXRlbXMvQ3VycmVuY3kvU2V0dGxlcnMvVmlsbGFnZVJ1bmUxIiwic2NhbGUiOjF9XQ/98d663edbd/VillageRune1.png","category":"Runegrafts","detailsId":"runegraft-of-the-fortress"},{"id":"runegraft-of-the-soulwick","name":"Runegraft of the Soulwick","image":"/gen/image/WzI1LDE0LHsiZiI6IjJESXRlbXMvQ3VycmVuY3kvU2V0dGxlcnMvVmlsbGFnZVJ1bmUxMiIsInNjYWxlIjoxfV0/6a9ec770d5/VillageRune12.png","category":"Runegrafts","detailsId":"runegraft-of-the-soulwick"},{"id":"runegraft-of-the-warp","name":"Runegraft of the Warp","image":"/gen/image/WzI1LDE0LHsiZiI6IjJESXRlbXMvQ3VycmVuY3kvU2V0dGxlcnMvVmlsbGFnZVJ1bmUxMSIsInNjYWxlIjoxfV0/3a56530c4f/VillageRune11.png","category":"Runegrafts","detailsId":"runegraft-of-the-warp"}]}