{"core":{"items":[{"id":"chaos","name":"Chaos Orb","image":"/gen/image/WzI1LDE0LHsiZiI6IjJESXRlbXMvQ3VycmVuY3kvQ3VycmVuY3lSZXJvbGxSYXJlIiwic2NhbGUiOjF9XQ/46a2347805/CurrencyRerollRare.png","category":"Currency","detailsId":"chaos-orb"},{"id":"divine","name":"Divine Orb","image":"/gen/image/WzI1LDE0LHsiZiI6IjJESXRlbXMvQ3VycmVuY3kvQ3VycmVuY3lNb2RWYWx1ZXMiLCJzY2FsZSI6MX1d/ec48896769/CurrencyModValues.png","category":"Currency","detailsId":"divine-orb"}],"rates":{"divine":0.001495},"primary":"chaos","secondary":"divine"},"lines":[{"id":"runegraft-of-blasphemy","primaryValue":5,"volumePrimaryValue":40.83,"maxVolumeCurrency":"chaos","maxVolumeRate":0.2,"sparkline":{"totalChange":374.4,"data":[90.38,66.38,15.46,325.2,146.9,688.9,374.4]}},{"id":"runegraft-of-gemcraft","primaryValue":227.4,"volumePrimaryValue":303.2,"maxVolumeCurrency":"chaos","maxVolumeRate":0.004398,"sparkline":{"totalChange":5.88,"data":[-15.21,-15.42,-16.81,16.70,-43.17,-22.67,5.88]}},{"id":"runegraft-of-quaffing","primaryValue":2,"volumePrimaryValue":3.0,"maxVolumeCurrency":"chaos","maxVolumeRate":0.5,"sparkline":{"totalChange":-30.00,"data":[-22.36,-1.01,-6.67,-10.83,-28.02,177.7,-30.00]}},{"id":"runegraft-of-rallying","primaryValue":12,"volumePrimaryValue":2.00,"maxVolumeCurrency":"chaos","maxVolumeRate":0.08333,"sparkline":{"totalChange":233.3,"data":[-28.67,-11.95,-39.81,-18.47,-36.22,80.56,233.3]}},{"id":"runegraft-of-restitching","primaryValue":2.22,"volumePrimaryValue":13.33,"maxVolumeCurrency":"chaos","maxVolumeRate":0.45,"sparkline":{"totalChange":80.49,"data":[6.71,-15.01,69.62,310.8,275.3,122.8,80.49]}},{"id":"runegraft-of-stability","primaryValue":45.75,"volumePrimaryValue":30.50,"maxVolumeCurrency":"chaos","maxVolumeRate":0.02186,"sparkline":{"totalChange":-22.27,"data":[72.24,15.40,56.60,48.92,-20.83,10.20,-22.27]}},{"id":"runegraft-of-the-agile","primaryValue":1,"volumePrimaryValue":0.5,"maxVolumeCurrency":"chaos","maxVolumeRate":1,"sparkline":{"totalChange":-94.05,"data":[-76.08,-82.93,-50.53,-46.62,-66.73,-52.28,-94.05]}},{"id":"runegraft-of-the-combatant","primaryValue":1,"volumePrimaryValue":5.17,"maxVolumeCurrency":"chaos","maxVolumeRate":1,"sparkline":{"totalChange":-2.5,"data":[0.42,-0.33,70.31,164.8,49.38,280.6,-2.5]}},{"id":"runegraft-of-the-imbued","primaryValue":9,"volumePrimaryValue":4.5,"maxVolumeCurrency":"chaos","maxVolumeRate":0.1111,"sparkline":{"totalChange":82.81,"data":[-46.65,-37.85,-37.11,-11.64,20.07,95.34,82.81]}},{"id":"runegraft-of-the-jeweller","primaryValue":0.3333,"volumePrimaryValue":0.5000,"maxVolumeCurrency":"chaos","maxVolumeRate":3,"sparkline":{"totalChange":-66.67,"data":[23.77,0,198.4,189.5,193.3,-42.16,-66.67]}},{"id":"runegraft-of-the-novamark","primaryValue":8,"volumePrimaryValue":1.33,"maxVolumeCurrency":"chaos","maxVolumeRate":0.125,"sparkline":{"totalChange":700,"data":[162.4,0,41.11,161.3,508.3,285.7,700]}},{"id":"runegraft-of-the-river","primaryValue":0.3333,"volumePrimaryValue":1.17,"maxVolumeCurrency":"chaos","maxVolumeRate":3,"sparkline":{"totalChange":-93.33,"data":[20.59,0.57,1.43,-26.66,-35.55,5.64,-93.33]}},{"id":"runegraft-of-the-sinistral","primaryValue":1.1,"volumePrimaryValue":5.5,"maxVolumeCurrency":"chaos","maxVolumeRate":0.9091,"sparkline":{"totalChange":-76.84,"data":[-51.33,-69.40,-53.48,-53.65,-43.05,-12.31,-76.84]}},{"id":"runegraft-of-the-spellbound","primaryValue":5.5,"volumePrimaryValue":16.5,"maxVolumeCurrency":"chaos","maxVolumeRate":0.1818,"sparkline":{"totalChange":120,"data":[-17.14,-6.70,-7.83,36.98,105.5,182.6,120]}},{"id":"runegraft-of-the-witchmark","primaryValue":4,"volumePrimaryValue":3.33,"maxVolumeCurrency":"chaos","maxVolumeRate":0.25,"sparkline":{"totalChange":-63.04,"data":[-24.26,-41.82,-50.72,-20.35,-30.42,-18.14,-63.04]}},{"id":"runegraft-of-time","primaryValue":2.5,"volumePrimaryValue":6.67,"maxVolumeCurrency":"chaos","maxVolumeRate":0.4,"sparkline":{"totalChange":-34.09,"data":[51.84,32.00,161.4,-17.29,41.02,322.8,-34.09]}},{"id":"runegraft-of-treachery","primaryValue":9.28,"volumePrimaryValue":111.3,"maxVolumeCurrency":"chaos","maxVolumeRate":0.1078,"sparkline":{"totalChange":-30.51,"data":[-13.73,-12.46,-16.39,-10.15,-18.40,-12.42,-30.51]}},{"id":"runegraft-of-loyalty","primaryValue":1,"volumePrimaryValue":3,"maxVolumeCurrency":"chaos","maxVolumeRate":1,"sparkline":{"totalChange":-37.31,"data":[-11.75,-32.51,-22.78,55.58,75.20,32.34,-37.31]}},{"id":"runegraft-of-refraction","primaryValue":2,"volumePrimaryValue":3.67,"maxVolumeCurrency":"chaos","maxVolumeRate":0.5,"sparkline":{"totalChange":-14.63,"data":[5.89,-4.58,0.76,8.79,81.68,130.0,-14.63]}},{"id":"runegraft-of-resurgence","primaryValue":2.21,"volumePrimaryValue":8.83,"maxVolumeCurrency":"chaos","maxVolumeRate":0.4528,"sparkline":{"totalChange":-7.99,"data":[2.90,29.27,-12.12,31.31,-1.32,253.3,-7.99]}},{"id":"runegraft-of-rotblood","primaryValue":48,"volumePrimaryValue":40.00,"maxVolumeCurrency":"chaos","maxVolumeRate":0.02083,"sparkline":{"totalChange":-41.34,"data":[-20.07,-43.88,-10.18,-24.09,-42.87,-61.90,-41.34]}},{"id":"runegraft-of-suffering","primaryValue":2,"volumePrimaryValue":3.33,"maxVolumeCurrency":"chaos","maxVolumeRate":0.5,"sparkline":{"totalChange":-3.80,"data":[-58.80,-47.38,157.4,46.54,3.42,145.2,-3.80]}},{"id":"runegraft-of-the-bound","primaryValue":4,"volumePrimaryValue":0.6667,"maxVolumeCurrency":"chaos","maxVolumeRate":0.25,"sparkline":{"totalChange":-46.24,"data":[-11.37,-23.30,-13.08,-15.14,50.82,37.71,-46.24]}},{"id":"runegraft-of-the-fortress","primaryValue":805.6,"volumePrimaryValue":3222,"maxVolumeCurrency":"chaos","maxVolumeRate":0.001241,"sparkline":{"totalChange":16.19,"data":[9.50,17.48,9.14,6.13,1.90,2.64,16.19]}},{"id":"runegraft-of-the-soulwick","primaryValue":130.5,"volumePrimaryValue":43.50,"maxVolumeCurrency":"chaos","maxVolumeRate":0.007663,"sparkline":{"totalChange":119.9,"data":[499.1,315.2,383.7,637.4,104.5,135.5,119.9]}},{"id":"runegraft-of-the-warp","primaryValue":985.1,"volumePrimaryValue":2463,"maxVolumeCurrency":"chaos","maxVolumeRate":0.001015,"sparkline":{"totalChange":17.51,"data":[-5.17,-10.05,-7.50,-2.42,-13.36,-6.69,17.51]}},{"id":"runegraft-of-fury","primaryValue":1,"volumePrimaryValue":0.1667,"maxVolumeCurrency":"chaos","maxVolumeRate":1,"sparkline":{"totalChange":-98,"data":[-67.90,-86.44,-89.70,-75.11,-96.58,-95.83,-98]}}],"items":[{"id":"runegraft-of-blasphemy","name":"Runegraft of Blasphemy","image":"/gen/image/WzI1LDE0LHsiZiI6IjJESXRlbXMvQ3VycmVuY3kvU2V0dGxlcnMvVmlsbGFnZVJ1bmUxNSIsInNjYWxlIjoxfV0/a2bc8d267f/VillageRune15.png","category":"Runegrafts","detailsId":"runegraft-of-blasphemy"},{"id":"runegraft-of-gemcraft","name":"Runegraft of Gemcraft","image":"/gen/image/WzI1LDE0LHsiZiI6IjJESXRlbXMvQ3VycmVuY3kvU2V0dGxlcnMvVmlsbGFnZVJ1bmUxNCIsInNjYWxlIjoxfV0/6288329dc0/VillageRune14.png","category":"Runegrafts","detailsId":"runegraft-of-gemcraft"},{"id":"runegraft-of-quaffing","name":"Runegraft of Quaffing","image":"/gen/image/WzI1LDE0LHsiZiI6IjJESXRlbXMvQ3VycmVuY3kvU2V0dGxlcnMvVmlsbGFnZVJ1bmUyMSIsInNjYWxlIjoxfV0/d9dc5f6d05/VillageRune21.png","category":"Runegrafts","detailsId":"runegraft-of-quaffing"},{"id":"runegraft-of-rallying","name":"Runegraft of Rallying","image":"/gen/image/WzI1LDE0LHsiZiI6IjJESXRlbXMvQ3VycmVuY3kvU2V0dGxlcnMvVmlsbGFnZVJ1bmUzNyIsInNjYWxlIjoxfV0/45985fdb24/VillageRune37.png","category":"Runegrafts","detailsId":"runegraft-of-rallying"},{"id":"runegraft-of-restitching","name":"Runegraft of Restitching","image":"/gen/image/WzI1LDE0LHsiZiI6IjJESXRlbXMvQ3VycmVuY3kvU2V0dGxlcnMvVmlsbGFnZVJ1bmUyMiIsInNjYWxlIjoxfV0/84a974b87d/VillageRune22.png","category":"Runegrafts","detailsId":"runegraft-of-restitching"},{"id":"runegraft-of-stability","name":"Runegraft of Stability","image":"/gen/image/WzI1LDE0LHsiZiI6IjJESXRlbXMvQ3VycmVuY3kvU2V0dGxlcnMvVmlsbGFnZVJ1bmUyIiwic2NhbGUiOjF9XQ/c0bfc39082/VillageRune2.png","category":"Runegrafts","detailsId":"runegraft-of-stability"},{"id":"runegraft-of-the-agile","name":"Runegraft of the Agile","image":"/gen/image/WzI1LDE0LHsiZiI6IjJESXRlbXMvQ3VycmVuY3kvU2V0dGxlcnMvVmlsbGFnZVJ1bmUzMiIsInNjYWxlIjoxfV0/20d6340a74/VillageRune32.png","category":"Runegrafts","detailsId":"runegraft-of-the-agile"},{"id":"runegraft-of-the-combatant","name":"Runegraft of the Combatant","image":"/gen/image/WzI1LDE0LHsiZiI6IjJESXRlbXMvQ3VycmVuY3kvU2V0dGxlcnMvVmlsbGFnZVJ1bmU0Iiwic2NhbGUiOjF9XQ/81bdd89a32/VillageRune4.png","category":"Runegrafts","detailsId":"runegraft-of-the-combatant"},{"id":"runegraft-of-the-imbued","name":"Runegraft of the Imbued","image":"/gen/image/WzI1LDE0LHsiZiI6IjJESXRlbXMvQ3VycmVuY3kvU2V0dGxlcnMvVmlsbGFnZVJ1bmUzMCIsInNjYWxlIjoxfV0/63d0c522fb/VillageRune30.png","category":"Runegrafts","detailsId":"runegraft-of-the-imbued"},{"id":"runegraft-of-the-jeweller","name":"Runegraft of the Jeweller","image":"/gen/image/WzI1LDE0LHsiZiI6IjJESXRlbXMvQ3VycmVuY3kvU2V0dGxlcnMvVmlsbGFnZVJ1bmU4Iiwic2NhbGUiOjF9XQ/f5ea7b3aa9/VillageRune8.png","category":"Runegrafts","detailsId":"runegraft-of-the-jeweller"},{"id":"runegraft-of-the-novamark","name":"Runegraft of the Novamark","image":"/gen/image/WzI1LDE0LHsiZiI6IjJESXRlbXMvQ3VycmVuY3kvU2V0dGxlcnMvVmlsbGFnZVJ1bmUyNSIsInNjYWxlIjoxfV0/fb0f9a5935/VillageRune25.png","category":"Runegrafts","detailsId":"runegraft-of-the-novamark"},{"id":"runegraft-of-the-river","name":"Runegraft of the River","image":"/gen/image/WzI1LDE0LHsiZiI6IjJESXRlbXMvQ3VycmVuY3kvU2V0dGxlcnMvVmlsbGFnZVJ1bmU1Iiwic2NhbGUiOjF9XQ/239b52bb4d/VillageRune5.png","category":"Runegrafts","detailsId":"runegraft-of-the-river"},{"id":"runegraft-of-the-sinistral","name":"Runegraft of the Sinistral","image":"/gen/image/WzI1LDE0LHsiZiI6IjJESXRlbXMvQ3VycmVuY3kvU2V0dGxlcnMvVmlsbGFnZVJ1bmU2Iiwic2NhbGUiOjF9XQ/2eed968220/VillageRune6.png","category":"Runegrafts","detailsId":"runegraft-of-the-sinistral"},{"id":"runegraft-of-the-spellbound","name":"Runegraft of the Spellbound","image":"/gen/image/WzI1LDE0LHsiZiI6IjJESXRlbXMvQ3VycmVuY3kvU2V0dGxlcnMvVmlsbGFnZVJ1bmUyNiIsInNjYWxlIjoxfV0/e19a7e066a/VillageRune26.png","category":"Runegrafts","detailsId":"runegraft-of-the-spellbound"},{"id":"runegraft-of-the-witchmark","name":"Runegraft of the Witchmark","image":"/gen/image/WzI1LDE0LHsiZiI6IjJESXRlbXMvQ3VycmVuY3kvU2V0dGxlcnMvVmlsbGFnZVJ1bmUyNCIsInNjYWxlIjoxfV0/b83d8d141d/VillageRune24.png","category":"Runegrafts","detailsId":"runegraft-of-the-witchmark"},{"id":"runegraft-of-time","name":"Runegraft of Time","image":"/gen/image/WzI1LDE0LHsiZiI6IjJESXRlbXMvQ3VycmVuY3kvU2V0dGxlcnMvVmlsbGFnZVJ1bmUxOSIsInNjYWxlIjoxfV0/9c1836484c/VillageRune19.png","category":"Runegrafts","detailsId":"runegraft-of-time"},{"id":"runegraft-of-treachery","name":"Runegraft of Treachery","image":"/gen/image/WzI1LDE0LHsiZiI6IjJESXRlbXMvQ3VycmVuY3kvU2V0dGxlcnMvVmlsbGFnZVJ1bmUyMCIsInNjYWxlIjoxfV0/6f462c33f6/VillageRune20.png","category":"Runegrafts","detailsId":"runegraft-of-treachery"},{"id":"runegraft-of-loyalty","name":"Runegraft of Loyalty","image":"/gen/image/WzI1LDE0LHsiZiI6IjJESXRlbXMvQ3VycmVuY3kvU2V0dGxlcnMvVmlsbGFnZVJ1bmUyMyIsInNjYWxlIjoxfV0/b856c79baa/VillageRune23.png","category":"Runegrafts","detailsId":"runegraft-of-loyalty"},{"id":"runegraft-of-refraction","name":"Runegraft of Refraction","image":"/gen/image/WzI1LDE0LHsiZiI6IjJESXRlbXMvQ3VycmVuY3kvU2V0dGxlcnMvVmlsbGFnZVJ1bmU3Iiwic2NhbGUiOjF9XQ/953733102b/VillageRune7.png","category":"Runegrafts","detailsId":"runegraft-of-refraction"},{"id":"runegraft-of-resurgence","name":"Runegraft of Resurgence","image":"/gen/image/WzI1LDE0LHsiZiI6IjJESXRlbXMvQ3VycmVuY3kvU2V0dGxlcnMvVmlsbGFnZVJ1bmUzMSIsInNjYWxlIjoxfV0/fd0ff25805/VillageRune31.png","category":"Runegrafts","detailsId":"runegraft-of-resurgence"},{"id":"runegraft-of-rotblood","name":"Runegraft of Rotblood","image":"/gen/image/WzI1LDE0LHsiZiI6IjJESXRlbXMvQ3VycmVuY3kvU2V0dGxlcnMvVmlsbGFnZVJ1bmUzMyIsInNjYWxlIjoxfV0/57870db175/VillageRune33.png","category":"Runegrafts","detailsId":"runegraft-of-rotblood"},{"id":"runegraft-of-suffering","name":"Runegraft of Suffering","image":"/gen/image/WzI1LDE0LHsiZiI6IjJESXRlbXMvQ3VycmVuY3kvU2V0dGxlcnMvVmlsbGFnZVJ1bmUyNyIsInNjYWxlIjoxfV0/4095f212ff/VillageRune27.png","category":"Runegrafts","detailsId":"runegraft-of-suffering"},{"id":"runegraft-of-the-bound","name":"Runegraft of the Bound","image":"/gen/image/WzI1LDE0LHsiZiI6IjJESXRlbXMvQ3VycmVuY3kvU2V0dGxlcnMvVmlsbGFnZVJ1bmUzIiwic2NhbGUiOjF9XQ/7e7fa2cc52/VillageRune3.png","category":"Runegrafts","detailsId":"runegraft-of-the-bound"},{"id":"runegraft-of-the-fortress","name":"Runegraft of the Fortress","image":"/gen/image/WzI1LDE0LHsiZiI6IjJESXRlbXMvQ3VycmVuY3kvU2V0dGxlcnMvVmlsbGFnZVJ1bmUxIiwic2NhbGUiOjF9XQ/98d663edbd/VillageRune1.png","category":"Runegrafts","detailsId":"runegraft-of-the-fortress"},{"id":"runegraft-of-the-soulwick","name":"Runegraft of the Soulwick","image":"/gen/image/WzI1LDE0LHsiZiI6IjJESXRlbXMvQ3VycmVuY3kvU2V0dGxlcnMvVmlsbGFnZVJ1bmUxMiIsInNjYWxlIjoxfV0/6a9ec770d5/VillageRune12.png","category":"Runegrafts","detailsId":"runegraft-of-the-soulwick"},{"id":"runegraft-of-the-warp","name":"Runegraft of the Warp","image":"/gen/image/WzI1LDE0LHsiZiI6IjJESXRlbXMvQ3VycmVuY3kvU2V0dGxlcnMvVmlsbGFnZVJ1bmUxMSIsInNjYWxlIjoxfV0/3a56530c4f/VillageRune11.png","category":"Runegrafts","detailsId":"runegraft-of-the-warp"},{"id":"runegraft-of-fury","name":"Runegraft of Fury","image":"/gen/image/WzI1LDE0LHsiZiI6IjJESXRlbXMvQ3VycmVuY3kvU2V0dGxlcnMvVmlsbGFnZVJ1bmUzNCIsInNjYWxlIjoxfV0/c453ece978/VillageRune34.png","category":"Runegrafts","detailsId":"runegraft-of-fury"}]}