{"core":{"items":[{"id":"chaos","name":"Chaos Orb","image":"/gen/image/WzI1LDE0LHsiZiI6IjJESXRlbXMvQ3VycmVuY3kvQ3VycmVuY3lSZXJvbGxSYXJlIiwic2NhbGUiOjF9XQ/46a2347805/CurrencyRerollRare.png","category":"Currency","detailsId":"chaos-orb"},{"id":"divine","name":"Divine Orb","image":"/gen/image/WzI1LDE0LHsiZiI6IjJESXRlbXMvQ3VycmVuY3kvQ3VycmVuY3lNb2RWYWx1ZXMiLCJzY2FsZSI6MX1d/ec48896769/CurrencyModValues.png","category":"Currency","detailsId":"divine-orb"}],"rates":{"divine":0.002562},"primary":"chaos","secondary":"divine"},"lines":[{"id":"abyss-scarab-of-emptiness","primaryValue":0.3659,"volumePrimaryValue":57.50,"maxVolumeCurrency":"chaos","maxVolumeRate":2.73,"sparkline":{"totalChange":-12.73,"data":[44.19,-3.93,-3.64,22.96,10.93,124.8,-12.73]}},{"id":"abyss-scarab-of-profound-depth","primaryValue":0.4900,"volumePrimaryValue":20.33,"maxVolumeCurrency":"chaos","maxVolumeRate":2.04,"sparkline":{"totalChange":-70.78,"data":[-25.03,-15.80,5.80,-9.64,77.49,-29.42,-70.78]}},{"id":"ambush-scarab","primaryValue":0.4795,"volumePrimaryValue":6238,"maxVolumeCurrency":"chaos","maxVolumeRate":2.09,"sparkline":{"totalChange":-1.74,"data":[2.49,-17.32,-22.48,-4.71,38.50,13.03,-1.74]}},{"id":"ambush-scarab-of-containment","primaryValue":247.4,"volumePrimaryValue":233090,"maxVolumeCurrency":"chaos","maxVolumeRate":0.004042,"sparkline":{"totalChange":-24.67,"data":[-11.56,-14.49,-21.24,-26.55,-32.22,-37.59,-24.67]}},{"id":"ambush-scarab-of-discernment","primaryValue":0.7412,"volumePrimaryValue":3519,"maxVolumeCurrency":"chaos","maxVolumeRate":1.35,"sparkline":{"totalChange":27.71,"data":[-9.50,-10.25,38.37,-19.72,46.80,27.42,27.71]}},{"id":"ambush-scarab-of-hidden-compartments","primaryValue":0.1803,"volumePrimaryValue":1585,"maxVolumeCurrency":"chaos","maxVolumeRate":5.55,"sparkline":{"totalChange":-5.22,"data":[40.75,53.12,60.26,56.45,56.56,27.35,-5.22]}},{"id":"ambush-scarab-of-potency","primaryValue":0.2823,"volumePrimaryValue":2089,"maxVolumeCurrency":"chaos","maxVolumeRate":3.54,"sparkline":{"totalChange":-19.74,"data":[-22.71,-10.76,-17.53,5.14,-0.44,-5.05,-19.74]}},{"id":"anarchy-scarab-of-gigantification","primaryValue":0.1971,"volumePrimaryValue":464.5,"maxVolumeCurrency":"chaos","maxVolumeRate":5.07,"sparkline":{"totalChange":35.91,"data":[44.58,19.85,44.64,74.08,76.86,-6.64,35.91]}},{"id":"anarchy-scarab-of-partnership","primaryValue":0.2005,"volumePrimaryValue":26.00,"maxVolumeCurrency":"chaos","maxVolumeRate":4.99,"sparkline":{"totalChange":-3.20,"data":[18.52,19.94,19.40,5.64,12.87,11.83,-3.20]}},{"id":"betrayal-scarab-of-perpetuation","primaryValue":0.6997,"volumePrimaryValue":959.3,"maxVolumeCurrency":"chaos","maxVolumeRate":1.43,"sparkline":{"totalChange":44.12,"data":[7.93,28.27,-6.14,18.78,31.24,-21.52,44.12]}},{"id":"betrayal-scarab-of-the-allflame","primaryValue":0.3068,"volumePrimaryValue":345.0,"maxVolumeCurrency":"chaos","maxVolumeRate":3.26,"sparkline":{"totalChange":19.07,"data":[39.12,11.57,-7.07,15.50,28.12,17.50,19.07]}},{"id":"beyond-scarab","primaryValue":0.3258,"volumePrimaryValue":647.5,"maxVolumeCurrency":"chaos","maxVolumeRate":3.07,"sparkline":{"totalChange":50.36,"data":[5.33,0.02,0.29,40.29,47.37,49.55,50.36]}},{"id":"beyond-scarab-of-resurgence","primaryValue":0.5837,"volumePrimaryValue":1545,"maxVolumeCurrency":"chaos","maxVolumeRate":1.71,"sparkline":{"totalChange":71.10,"data":[82.26,93.12,73.07,41.57,60.69,17.10,71.10]}},{"id":"blight-scarab","primaryValue":0.3070,"volumePrimaryValue":572.2,"maxVolumeCurrency":"chaos","maxVolumeRate":3.26,"sparkline":{"totalChange":18.20,"data":[-0.24,5.69,-2.03,-5.43,8.39,12.43,18.20]}},{"id":"blight-scarab-of-invigoration","primaryValue":5.74,"volumePrimaryValue":742.8,"maxVolumeCurrency":"chaos","maxVolumeRate":0.1743,"sparkline":{"totalChange":22.41,"data":[-0.43,7.11,12.98,6.62,5.26,13.71,22.41]}},{"id":"blight-scarab-of-the-blightheart","primaryValue":0.4574,"volumePrimaryValue":157.5,"maxVolumeCurrency":"chaos","maxVolumeRate":2.19,"sparkline":{"totalChange":-16.55,"data":[41.16,12.59,-2.96,7.54,-4.73,16.51,-16.55]}},{"id":"breach-scarab-of-lordship","primaryValue":1.55,"volumePrimaryValue":13823,"maxVolumeCurrency":"chaos","maxVolumeRate":0.6440,"sparkline":{"totalChange":-51.44,"data":[-5.11,-31.18,-48.44,-37.87,-42.04,-43.77,-51.44]}},{"id":"breach-scarab-of-splintering","primaryValue":0.3739,"volumePrimaryValue":996.0,"maxVolumeCurrency":"chaos","maxVolumeRate":2.67,"sparkline":{"totalChange":-20.13,"data":[24.82,22.68,23.52,35.95,25.47,105.8,-20.13]}},{"id":"cartography-scarab-of-escalation","primaryValue":0.3124,"volumePrimaryValue":1829,"maxVolumeCurrency":"chaos","maxVolumeRate":3.20,"sparkline":{"totalChange":10.79,"data":[-3.30,-8.16,-2.41,0.81,17.91,9.60,10.79]}},{"id":"abyss-scarab","primaryValue":0.3930,"volumePrimaryValue":217.7,"maxVolumeCurrency":"chaos","maxVolumeRate":2.54,"sparkline":{"totalChange":9.52,"data":[0.54,-3.97,-9.87,34.59,1.23,4.67,9.52]}},{"id":"abyss-scarab-of-edifice","primaryValue":0.2806,"volumePrimaryValue":18.33,"maxVolumeCurrency":"chaos","maxVolumeRate":3.56,"sparkline":{"totalChange":-47.54,"data":[-11.93,-19.04,8.59,-3.35,-25.31,20.68,-47.54]}},{"id":"abyss-scarab-of-multitudes","primaryValue":0.3416,"volumePrimaryValue":269.7,"maxVolumeCurrency":"chaos","maxVolumeRate":2.93,"sparkline":{"totalChange":30.68,"data":[41.90,10.25,27.17,69.69,82.62,58.34,30.68]}},{"id":"anarchy-scarab","primaryValue":0.3326,"volumePrimaryValue":1337,"maxVolumeCurrency":"chaos","maxVolumeRate":3.01,"sparkline":{"totalChange":43.81,"data":[7.01,6.43,14.91,23.38,32.80,50.14,43.81]}},{"id":"anarchy-scarab-of-the-exceptional","primaryValue":0.2218,"volumePrimaryValue":35.33,"maxVolumeCurrency":"chaos","maxVolumeRate":4.51,"sparkline":{"totalChange":34.81,"data":[48.42,65.09,41.11,20.80,62.72,63.01,34.81]}},{"id":"bestiary-scarab","primaryValue":0.3611,"volumePrimaryValue":633.5,"maxVolumeCurrency":"chaos","maxVolumeRate":2.77,"sparkline":{"totalChange":68.33,"data":[35.71,22.48,35.02,53.93,85.09,53.48,68.33]}},{"id":"bestiary-scarab-of-duplicating","primaryValue":2.21,"volumePrimaryValue":13511,"maxVolumeCurrency":"chaos","maxVolumeRate":0.4528,"sparkline":{"totalChange":-11.69,"data":[-10.88,14.81,-0.68,1.91,-9.82,-10.74,-11.69]}},{"id":"bestiary-scarab-of-the-herd","primaryValue":1.15,"volumePrimaryValue":11936,"maxVolumeCurrency":"chaos","maxVolumeRate":0.8698,"sparkline":{"totalChange":-38.39,"data":[-37.63,-26.86,-29.58,-19.94,-30.56,-36.10,-38.39]}},{"id":"betrayal-scarab","primaryValue":0.3367,"volumePrimaryValue":1142,"maxVolumeCurrency":"chaos","maxVolumeRate":2.97,"sparkline":{"totalChange":116.1,"data":[31.53,33.95,67.15,105.4,112.7,99.29,116.1]}},{"id":"betrayal-scarab-of-reinforcements","primaryValue":0.3555,"volumePrimaryValue":414.8,"maxVolumeCurrency":"chaos","maxVolumeRate":2.81,"sparkline":{"totalChange":11.65,"data":[28.80,5.21,1.56,21.79,32.30,37.15,11.65]}},{"id":"beyond-scarab-of-haemophilia","primaryValue":0.4435,"volumePrimaryValue":715.0,"maxVolumeCurrency":"chaos","maxVolumeRate":2.26,"sparkline":{"totalChange":102.6,"data":[8.97,10.62,-0.02,72.13,34.17,24.78,102.6]}},{"id":"beyond-scarab-of-the-invasion","primaryValue":1.15,"volumePrimaryValue":1594,"maxVolumeCurrency":"chaos","maxVolumeRate":0.8695,"sparkline":{"totalChange":78.13,"data":[-1.95,13.60,-25.68,-0.82,-7.63,-0.29,78.13]}},{"id":"blight-scarab-of-blooming","primaryValue":10.68,"volumePrimaryValue":1896,"maxVolumeCurrency":"chaos","maxVolumeRate":0.09364,"sparkline":{"totalChange":14.40,"data":[-18.31,-20.28,-20.73,-8.74,-14.49,-3.62,14.40]}},{"id":"breach-scarab","primaryValue":0.1863,"volumePrimaryValue":200.3,"maxVolumeCurrency":"chaos","maxVolumeRate":5.37,"sparkline":{"totalChange":-27.36,"data":[-8.16,-8.04,1.15,5.58,8.37,8.51,-27.36]}},{"id":"breach-scarab-of-resonant-cascade","primaryValue":50.26,"volumePrimaryValue":41657,"maxVolumeCurrency":"chaos","maxVolumeRate":0.01990,"sparkline":{"totalChange":-8.42,"data":[-10.57,-12.39,-4.01,-7.83,-16.24,-8.19,-8.42]}},{"id":"breach-scarab-of-snares","primaryValue":2.1,"volumePrimaryValue":651.0,"maxVolumeCurrency":"chaos","maxVolumeRate":0.4762,"sparkline":{"totalChange":-25.81,"data":[13.08,-5.14,2.87,22.39,15.89,-10.90,-25.81]}},{"id":"cartography-scarab-of-corruption","primaryValue":0.6215,"volumePrimaryValue":2128,"maxVolumeCurrency":"chaos","maxVolumeRate":1.61,"sparkline":{"totalChange":18.13,"data":[-11.96,-17.65,2.89,5.56,-0.69,23.92,18.13]}},{"id":"cartography-scarab-of-risk","primaryValue":129.9,"volumePrimaryValue":204694,"maxVolumeCurrency":"chaos","maxVolumeRate":0.007699,"sparkline":{"totalChange":14.78,"data":[2.62,7.62,17.75,51.55,58.69,42.80,14.78]}},{"id":"cartography-scarab-of-the-multitude","primaryValue":0.3849,"volumePrimaryValue":1395,"maxVolumeCurrency":"chaos","maxVolumeRate":2.60,"sparkline":{"totalChange":36.62,"data":[3.69,13.01,23.70,32.45,12.42,18.37,36.62]}},{"id":"delirium-scarab-of-delusions","primaryValue":0.6809,"volumePrimaryValue":330.7,"maxVolumeCurrency":"chaos","maxVolumeRate":1.47,"sparkline":{"totalChange":-13.85,"data":[-26.84,-10.81,-18.80,-21.05,-8.12,78.08,-13.85]}},{"id":"delirium-scarab-of-paranoia","primaryValue":21.98,"volumePrimaryValue":102902,"maxVolumeCurrency":"chaos","maxVolumeRate":0.04549,"sparkline":{"totalChange":61.31,"data":[10.52,26.75,35.83,64.25,64.28,61.91,61.31]}},{"id":"divination-scarab-of-the-cloister","primaryValue":10.62,"volumePrimaryValue":316474,"maxVolumeCurrency":"chaos","maxVolumeRate":0.09417,"sparkline":{"totalChange":-30.43,"data":[31.84,53.75,17.52,11.19,-6.96,-17.38,-30.43]}},{"id":"domination-scarab","primaryValue":0.3799,"volumePrimaryValue":2235,"maxVolumeCurrency":"chaos","maxVolumeRate":2.63,"sparkline":{"totalChange":45.79,"data":[23.31,40.20,28.49,38.79,44.12,36.54,45.79]}},{"id":"domination-scarab-of-apparitions","primaryValue":0.2247,"volumePrimaryValue":531.7,"maxVolumeCurrency":"chaos","maxVolumeRate":4.45,"sparkline":{"totalChange":33.56,"data":[26.52,6.39,26.07,32.20,56.40,40.59,33.56]}},{"id":"essence-scarab","primaryValue":0.2490,"volumePrimaryValue":1597,"maxVolumeCurrency":"chaos","maxVolumeRate":4.02,"sparkline":{"totalChange":-9.78,"data":[7.48,13.66,3.37,22.33,24.62,9.79,-9.78]}},{"id":"essence-scarab-of-adaptation","primaryValue":1.19,"volumePrimaryValue":1188,"maxVolumeCurrency":"chaos","maxVolumeRate":0.8383,"sparkline":{"totalChange":-55.70,"data":[18.65,-12.11,9.29,158.9,27.59,15.45,-55.70]}},{"id":"essence-scarab-of-ascent","primaryValue":0.3448,"volumePrimaryValue":500.8,"maxVolumeCurrency":"chaos","maxVolumeRate":2.90,"sparkline":{"totalChange":-35.54,"data":[-7.94,-0.45,-16.24,-8.80,-11.93,-0.16,-35.54]}},{"id":"expedition-scarab","primaryValue":0.4552,"volumePrimaryValue":486.2,"maxVolumeCurrency":"chaos","maxVolumeRate":2.20,"sparkline":{"totalChange":66.07,"data":[26.56,15.04,31.80,60.72,64.64,39.52,66.07]}},{"id":"expedition-scarab-of-archaeology","primaryValue":0.6775,"volumePrimaryValue":132.3,"maxVolumeCurrency":"chaos","maxVolumeRate":1.48,"sparkline":{"totalChange":60.04,"data":[16.55,-0.87,3.37,-4.04,12.92,13.81,60.04]}},{"id":"harvest-scarab","primaryValue":0.2599,"volumePrimaryValue":348.3,"maxVolumeCurrency":"chaos","maxVolumeRate":3.85,"sparkline":{"totalChange":28.72,"data":[28.80,30.07,21.10,34.92,62.57,49.80,28.72]}},{"id":"harvest-scarab-of-doubling","primaryValue":13.95,"volumePrimaryValue":77685,"maxVolumeCurrency":"chaos","maxVolumeRate":0.07169,"sparkline":{"totalChange":35.88,"data":[4.06,2.18,17.93,30.19,32.22,27.99,35.88]}},{"id":"horned-scarab-of-awakening","primaryValue":48.62,"volumePrimaryValue":58797,"maxVolumeCurrency":"chaos","maxVolumeRate":0.02057,"sparkline":{"totalChange":-17.53,"data":[-0.10,1.41,-4.30,1.57,-10.49,-14.16,-17.53]}},{"id":"horned-scarab-of-bloodlines","primaryValue":417.6,"volumePrimaryValue":404594,"maxVolumeCurrency":"chaos","maxVolumeRate":0.002395,"sparkline":{"totalChange":-14.97,"data":[-4.00,4.94,-4.34,2.63,-5.57,-10.94,-14.97]}},{"id":"horned-scarab-of-glittering","primaryValue":3.18,"volumePrimaryValue":2350,"maxVolumeCurrency":"chaos","maxVolumeRate":0.3140,"sparkline":{"totalChange":86.45,"data":[15.28,7.28,-11.00,13.41,-6.20,15.60,86.45]}},{"id":"horned-scarab-of-nemeses","primaryValue":0.3827,"volumePrimaryValue":427.2,"maxVolumeCurrency":"chaos","maxVolumeRate":2.61,"sparkline":{"totalChange":11.93,"data":[-15.79,-15.78,16.61,83.37,24.31,2.81,11.93]}},{"id":"horned-scarab-of-pandemonium","primaryValue":254.7,"volumePrimaryValue":285759,"maxVolumeCurrency":"chaos","maxVolumeRate":0.003926,"sparkline":{"totalChange":51.08,"data":[2.37,8.38,11.13,47.15,82.95,60.00,51.08]}},{"id":"horned-scarab-of-preservation","primaryValue":360.8,"volumePrimaryValue":21165,"maxVolumeCurrency":"chaos","maxVolumeRate":0.002772,"sparkline":{"totalChange":22.00,"data":[1.58,4.53,3.61,11.23,11.30,13.10,22.00]}},{"id":"incursion-scarab","primaryValue":0.1996,"volumePrimaryValue":333.3,"maxVolumeCurrency":"chaos","maxVolumeRate":5.01,"sparkline":{"totalChange":0.37,"data":[12.71,-1.08,17.75,42.65,52.75,59.04,0.37]}},{"id":"incursion-scarab-of-champions","primaryValue":0.4632,"volumePrimaryValue":261.0,"maxVolumeCurrency":"chaos","maxVolumeRate":2.16,"sparkline":{"totalChange":11.89,"data":[2.91,3.07,73.41,57.12,-10.83,2.70,11.89]}},{"id":"influencing-scarab-of-hordes","primaryValue":0.3426,"volumePrimaryValue":1179,"maxVolumeCurrency":"chaos","maxVolumeRate":2.92,"sparkline":{"totalChange":-13.69,"data":[-11.23,13.52,-14.05,-13.64,-9.91,-22.81,-13.69]}},{"id":"influencing-scarab-of-the-elder","primaryValue":0.2589,"volumePrimaryValue":854.5,"maxVolumeCurrency":"chaos","maxVolumeRate":3.86,"sparkline":{"totalChange":26.88,"data":[24.33,10.00,21.02,54.74,54.29,37.74,26.88]}},{"id":"influencing-scarab-of-the-shaper","primaryValue":0.3449,"volumePrimaryValue":1465,"maxVolumeCurrency":"chaos","maxVolumeRate":2.90,"sparkline":{"totalChange":132.8,"data":[70.69,80.88,69.89,128.2,106.1,109.1,132.8]}},{"id":"kalguuran-scarab","primaryValue":0.7095,"volumePrimaryValue":4367,"maxVolumeCurrency":"chaos","maxVolumeRate":1.41,"sparkline":{"totalChange":16.15,"data":[13.68,53.65,38.46,79.23,31.66,49.39,16.15]}},{"id":"kalguuran-scarab-of-enriching","primaryValue":0.7979,"volumePrimaryValue":736.8,"maxVolumeCurrency":"chaos","maxVolumeRate":1.25,"sparkline":{"totalChange":-43.80,"data":[-50.30,-2.88,-34.61,-41.67,-43.10,-24.39,-43.80]}},{"id":"kalguuran-scarab-of-guarded-riches","primaryValue":0.7180,"volumePrimaryValue":793.8,"maxVolumeCurrency":"chaos","maxVolumeRate":1.39,"sparkline":{"totalChange":126.3,"data":[11.51,34.24,21.30,31.22,9.07,46.99,126.3]}},{"id":"legion-scarab-of-command","primaryValue":1.50,"volumePrimaryValue":981.5,"maxVolumeCurrency":"chaos","maxVolumeRate":0.6646,"sparkline":{"totalChange":9.18,"data":[-7.30,0.18,9.76,-8.42,-3.77,-19.62,9.18]}},{"id":"legion-scarab-of-officers","primaryValue":2.16,"volumePrimaryValue":831.7,"maxVolumeCurrency":"chaos","maxVolumeRate":0.4631,"sparkline":{"totalChange":416.7,"data":[26.18,30.26,35.19,41.77,85.92,69.71,416.7]}},{"id":"ritual-scarab-of-abundance","primaryValue":2.08,"volumePrimaryValue":3334,"maxVolumeCurrency":"chaos","maxVolumeRate":0.4811,"sparkline":{"totalChange":-24.37,"data":[-12.30,-13.08,-23.94,8.96,-21.65,-10.80,-24.37]}},{"id":"ritual-scarab-of-corpses","primaryValue":2.01,"volumePrimaryValue":475.2,"maxVolumeCurrency":"chaos","maxVolumeRate":0.4984,"sparkline":{"totalChange":326.3,"data":[7.84,70.68,106.2,78.61,26.96,113.4,326.3]}},{"id":"ritual-scarab-of-wisps","primaryValue":1.29,"volumePrimaryValue":709.5,"maxVolumeCurrency":"chaos","maxVolumeRate":0.7764,"sparkline":{"totalChange":163.4,"data":[-25.21,-6.70,-25.18,-8.17,-20.74,-18.37,163.4]}},{"id":"scarab-of-divinity","primaryValue":0.2727,"volumePrimaryValue":759.2,"maxVolumeCurrency":"chaos","maxVolumeRate":3.67,"sparkline":{"totalChange":118.9,"data":[60.46,44.63,66.48,100.9,131.3,123.8,118.9]}},{"id":"scarab-of-monstrous-lineage","primaryValue":0.6840,"volumePrimaryValue":12975,"maxVolumeCurrency":"chaos","maxVolumeRate":1.46,"sparkline":{"totalChange":-18.47,"data":[0.89,-8.24,-6.46,-13.86,-12.17,-5.16,-18.47]}},{"id":"scarab-of-wisps","primaryValue":1.46,"volumePrimaryValue":10523,"maxVolumeCurrency":"chaos","maxVolumeRate":0.6851,"sparkline":{"totalChange":-27.40,"data":[-3.35,1.96,-10.48,0.95,-10.71,-21.87,-27.40]}},{"id":"sulphite-scarab","primaryValue":0.2872,"volumePrimaryValue":1135,"maxVolumeCurrency":"chaos","maxVolumeRate":3.48,"sparkline":{"totalChange":48.34,"data":[25.68,14.31,27.55,54.54,55.11,51.10,48.34]}},{"id":"sulphite-scarab-of-fumes","primaryValue":0.2069,"volumePrimaryValue":266.7,"maxVolumeCurrency":"chaos","maxVolumeRate":4.83,"sparkline":{"totalChange":-21.72,"data":[27.23,13.05,19.12,-6.39,7.44,2.57,-21.72]}},{"id":"torment-scarab-of-peculiarity","primaryValue":0.2461,"volumePrimaryValue":150.8,"maxVolumeCurrency":"chaos","maxVolumeRate":4.06,"sparkline":{"totalChange":35.70,"data":[10.17,-8.58,31.58,30.99,72.46,34.95,35.70]}},{"id":"ultimatum-scarab-of-catalysing","primaryValue":40.71,"volumePrimaryValue":41082,"maxVolumeCurrency":"chaos","maxVolumeRate":0.02456,"sparkline":{"totalChange":0.06,"data":[-14.38,-21.24,-11.58,5.52,12.54,-2.12,0.06]}},{"id":"ultimatum-scarab-of-inscription","primaryValue":0.8587,"volumePrimaryValue":967.7,"maxVolumeCurrency":"chaos","maxVolumeRate":1.16,"sparkline":{"totalChange":13.01,"data":[-26.57,-1.34,-25.32,21.69,-44.61,-38.49,13.01]}},{"id":"delirium-scarab","primaryValue":0.3133,"volumePrimaryValue":177.7,"maxVolumeCurrency":"chaos","maxVolumeRate":3.19,"sparkline":{"totalChange":-26.71,"data":[-21.33,-38.87,-33.45,-34.36,-14.34,-22.21,-26.71]}},{"id":"delirium-scarab-of-mania","primaryValue":1.66,"volumePrimaryValue":5209,"maxVolumeCurrency":"chaos","maxVolumeRate":0.6027,"sparkline":{"totalChange":12.00,"data":[23.70,27.37,33.71,46.63,50.89,111.0,12.00]}},{"id":"delirium-scarab-of-neuroses","primaryValue":1.20,"volumePrimaryValue":1252,"maxVolumeCurrency":"chaos","maxVolumeRate":0.8358,"sparkline":{"totalChange":-18.64,"data":[2.76,-2.84,24.56,75.26,27.44,297.6,-18.64]}},{"id":"divination-scarab-of-pilfering","primaryValue":10.90,"volumePrimaryValue":14153,"maxVolumeCurrency":"chaos","maxVolumeRate":0.09171,"sparkline":{"totalChange":-14.43,"data":[-8.75,24.80,40.39,69.05,35.62,27.36,-14.43]}},{"id":"divination-scarab-of-plenty","primaryValue":0.4177,"volumePrimaryValue":1976,"maxVolumeCurrency":"chaos","maxVolumeRate":2.39,"sparkline":{"totalChange":-66.58,"data":[-49.45,-41.31,-50.95,-42.93,-32.83,-57.91,-66.58]}},{"id":"domination-scarab-of-evolution","primaryValue":0.3528,"volumePrimaryValue":131.7,"maxVolumeCurrency":"chaos","maxVolumeRate":2.83,"sparkline":{"totalChange":16.81,"data":[26.73,6.15,-11.73,4.31,1.78,16.58,16.81]}},{"id":"domination-scarab-of-terrors","primaryValue":36.81,"volumePrimaryValue":42759,"maxVolumeCurrency":"chaos","maxVolumeRate":0.02717,"sparkline":{"totalChange":0.12,"data":[-5.82,-7.23,1.89,1.06,-11.28,-16.32,0.12]}},{"id":"essence-scarab-of-calcification","primaryValue":8.37,"volumePrimaryValue":10130,"maxVolumeCurrency":"chaos","maxVolumeRate":0.1195,"sparkline":{"totalChange":-39.23,"data":[-35.76,-29.83,-33.14,-40.35,-47.94,-31.56,-39.23]}},{"id":"essence-scarab-of-stability","primaryValue":0.2868,"volumePrimaryValue":1334,"maxVolumeCurrency":"chaos","maxVolumeRate":3.49,"sparkline":{"totalChange":29.67,"data":[19.37,29.16,53.16,0.41,36.33,27.24,29.67]}},{"id":"expedition-scarab-of-runefinding","primaryValue":0.9449,"volumePrimaryValue":785.5,"maxVolumeCurrency":"chaos","maxVolumeRate":1.06,"sparkline":{"totalChange":142.8,"data":[70.00,17.24,54.45,56.89,89.00,77.57,142.8]}},{"id":"expedition-scarab-of-the-skald","primaryValue":0.5594,"volumePrimaryValue":190.7,"maxVolumeCurrency":"chaos","maxVolumeRate":1.79,"sparkline":{"totalChange":-76.51,"data":[-78.73,-54.96,-77.82,-49.83,-76.06,-74.28,-76.51]}},{"id":"expedition-scarab-of-verisium-powder","primaryValue":0.4274,"volumePrimaryValue":451.0,"maxVolumeCurrency":"chaos","maxVolumeRate":2.34,"sparkline":{"totalChange":46.66,"data":[40.82,10.30,22.06,36.38,70.14,80.10,46.66]}},{"id":"harvest-scarab-of-cornucopia","primaryValue":53.47,"volumePrimaryValue":54883,"maxVolumeCurrency":"chaos","maxVolumeRate":0.01870,"sparkline":{"totalChange":-43.92,"data":[-2.21,-7.00,-15.33,-17.45,-23.10,-26.69,-43.92]}},{"id":"horned-scarab-of-tradition","primaryValue":1.78,"volumePrimaryValue":148.3,"maxVolumeCurrency":"chaos","maxVolumeRate":0.5607,"sparkline":{"totalChange":72.94,"data":[-9.79,-32.90,-10.41,-12.23,-19.10,3.79,72.94]}},{"id":"incursion-scarab-of-invasion","primaryValue":0.2101,"volumePrimaryValue":458.3,"maxVolumeCurrency":"chaos","maxVolumeRate":4.76,"sparkline":{"totalChange":30.65,"data":[59.96,35.29,35.37,74.53,63.75,133.2,30.65]}},{"id":"incursion-scarab-of-timelines","primaryValue":4.48,"volumePrimaryValue":3523,"maxVolumeCurrency":"chaos","maxVolumeRate":0.2232,"sparkline":{"totalChange":1.24,"data":[3.18,-2.15,-3.23,-9.14,-15.16,-6.65,1.24]}},{"id":"influencing-scarab-of-conversion","primaryValue":0.5914,"volumePrimaryValue":310.2,"maxVolumeCurrency":"chaos","maxVolumeRate":1.69,"sparkline":{"totalChange":168.5,"data":[60.09,35.38,72.84,82.00,69.60,65.62,168.5]}},{"id":"kalguuran-scarab-of-refinement","primaryValue":44.56,"volumePrimaryValue":21247,"maxVolumeCurrency":"chaos","maxVolumeRate":0.02244,"sparkline":{"totalChange":3.62,"data":[-4.83,-5.47,-6.85,-2.05,-2.09,-5.54,3.62]}},{"id":"legion-scarab","primaryValue":0.4313,"volumePrimaryValue":774.5,"maxVolumeCurrency":"chaos","maxVolumeRate":2.32,"sparkline":{"totalChange":23.66,"data":[20.02,1.60,12.67,44.59,30.23,31.70,23.66]}},{"id":"legion-scarab-of-eternal-conflict","primaryValue":19.55,"volumePrimaryValue":6611,"maxVolumeCurrency":"chaos","maxVolumeRate":0.05115,"sparkline":{"totalChange":20.87,"data":[-0.71,-2.87,-0.48,-3.49,10.66,52.69,20.87]}},{"id":"ritual-scarab-of-selectiveness","primaryValue":0.8825,"volumePrimaryValue":2290,"maxVolumeCurrency":"chaos","maxVolumeRate":1.13,"sparkline":{"totalChange":58.81,"data":[0.58,9.15,-2.99,40.77,10.72,69.38,58.81]}},{"id":"scarab-of-adversaries","primaryValue":0.3753,"volumePrimaryValue":1772,"maxVolumeCurrency":"chaos","maxVolumeRate":2.66,"sparkline":{"totalChange":8.24,"data":[-15.44,1.57,-0.51,-0.47,3.76,11.42,8.24]}},{"id":"scarab-of-radiant-storms","primaryValue":0.5761,"volumePrimaryValue":32.17,"maxVolumeCurrency":"chaos","maxVolumeRate":1.74,"sparkline":{"totalChange":17.94,"data":[38.21,81.14,146.8,58.62,80.73,219.0,17.94]}},{"id":"scarab-of-stability","primaryValue":0.3624,"volumePrimaryValue":60.33,"maxVolumeCurrency":"chaos","maxVolumeRate":2.76,"sparkline":{"totalChange":29.91,"data":[48.99,28.44,12.76,4.27,8.55,3.74,29.91]}},{"id":"scarab-of-the-dextral","primaryValue":0.5602,"volumePrimaryValue":1183,"maxVolumeCurrency":"chaos","maxVolumeRate":1.79,"sparkline":{"totalChange":-34.99,"data":[-25.67,-8.66,-33.55,-39.14,-25.54,-52.53,-34.99]}},{"id":"scarab-of-the-sinistral","primaryValue":1.01,"volumePrimaryValue":2180,"maxVolumeCurrency":"chaos","maxVolumeRate":0.9872,"sparkline":{"totalChange":146.3,"data":[63.99,30.05,4.88,142.6,27.03,-5.24,146.3]}},{"id":"titanic-scarab","primaryValue":0.3728,"volumePrimaryValue":1440,"maxVolumeCurrency":"chaos","maxVolumeRate":2.68,"sparkline":{"totalChange":-41.34,"data":[-53.38,-56.72,-43.98,-10.01,-33.70,-33.46,-41.34]}},{"id":"titanic-scarab-of-legend","primaryValue":1.11,"volumePrimaryValue":2454,"maxVolumeCurrency":"chaos","maxVolumeRate":0.9008,"sparkline":{"totalChange":33.27,"data":[-22.35,-28.01,142.1,21.40,10.71,65.23,33.27]}},{"id":"titanic-scarab-of-treasures","primaryValue":0.6717,"volumePrimaryValue":538.0,"maxVolumeCurrency":"chaos","maxVolumeRate":1.49,"sparkline":{"totalChange":67.80,"data":[-20.89,-18.29,-16.59,-21.94,-27.29,0.65,67.80]}},{"id":"torment-scarab","primaryValue":0.3049,"volumePrimaryValue":559.8,"maxVolumeCurrency":"chaos","maxVolumeRate":3.28,"sparkline":{"totalChange":90.39,"data":[39.11,25.58,46.00,75.50,81.84,77.14,90.39]}},{"id":"torment-scarab-of-possession","primaryValue":0.2034,"volumePrimaryValue":49.33,"maxVolumeCurrency":"chaos","maxVolumeRate":4.92,"sparkline":{"totalChange":-5.59,"data":[20.48,10.71,10.17,15.89,24.85,13.54,-5.59]}},{"id":"ultimatum-scarab","primaryValue":0.3217,"volumePrimaryValue":672.5,"maxVolumeCurrency":"chaos","maxVolumeRate":3.11,"sparkline":{"totalChange":58.53,"data":[22.94,18.90,9.69,33.93,73.74,55.31,58.53]}},{"id":"ultimatum-scarab-of-bribing","primaryValue":0.4218,"volumePrimaryValue":932.8,"maxVolumeCurrency":"chaos","maxVolumeRate":2.37,"sparkline":{"totalChange":11.46,"data":[-7.72,5.45,-20.47,25.76,-2.53,-2.15,11.46]}},{"id":"ultimatum-scarab-of-dueling","primaryValue":2.15,"volumePrimaryValue":401.0,"maxVolumeCurrency":"chaos","maxVolumeRate":0.4643,"sparkline":{"totalChange":405.9,"data":[70.43,91.51,93.18,81.89,140.3,118.8,405.9]}}],"items":[{"id":"abyss-scarab-of-emptiness","name":"Abyss Scarab of Descending","image":"/gen/image/WzI1LDE0LHsiZiI6IjJESXRlbXMvQ3VycmVuY3kvU2NhcmFicy9UaWVyNFNjYXJhYkFieXNzIiwic2NhbGUiOjF9XQ/c1d1da69d6/Tier4ScarabAbyss.png","category":"Fragments","detailsId":"abyss-scarab-of-descending"},{"id":"abyss-scarab-of-profound-depth","name":"Abyss Scarab of Profound Depth","image":"/gen/image/WzI1LDE0LHsiZiI6IjJESXRlbXMvQ3VycmVuY3kvU2NhcmFicy9BbHRUaWVyNFNjYXJhYkFieXNzIiwic2NhbGUiOjF9XQ/b40fb2422b/AltTier4ScarabAbyss.png","category":"Fragments","detailsId":"abyss-scarab-of-profound-depth"},{"id":"ambush-scarab","name":"Ambush Scarab","image":"/gen/image/WzI1LDE0LHsiZiI6IjJESXRlbXMvQ3VycmVuY3kvU2NhcmFicy9MZXNzZXJTY2FyYWJTdHJvbmdib3hlcyIsInNjYWxlIjoxfV0/137917584a/LesserScarabStrongboxes.png","category":"Fragments","detailsId":"ambush-scarab"},{"id":"ambush-scarab-of-containment","name":"Ambush Scarab of Containment","image":"/gen/image/WzI1LDE0LHsiZiI6IjJESXRlbXMvQ3VycmVuY3kvU2NhcmFicy9UaWVyNFNjYXJhYlN0cm9uZ2JveGVzIiwic2NhbGUiOjF9XQ/da665a65ee/Tier4ScarabStrongboxes.png","category":"Fragments","detailsId":"ambush-scarab-of-containment"},{"id":"ambush-scarab-of-discernment","name":"Ambush Scarab of Discernment","image":"/gen/image/WzI1LDE0LHsiZiI6IjJESXRlbXMvQ3VycmVuY3kvU2NhcmFicy9BbHRUaWVyNFNjYXJhYlN0cm9uZ2JveGVzIiwic2NhbGUiOjF9XQ/72722370df/AltTier4ScarabStrongboxes.png","category":"Fragments","detailsId":"ambush-scarab-of-discernment"},{"id":"ambush-scarab-of-hidden-compartments","name":"Ambush Scarab of Hidden Compartments","image":"/gen/image/WzI1LDE0LHsiZiI6IjJESXRlbXMvQ3VycmVuY3kvU2NhcmFicy9Ob3JtYWxTY2FyYWJTdHJvbmdib3hlcyIsInNjYWxlIjoxfV0/2654dacfee/NormalScarabStrongboxes.png","category":"Fragments","detailsId":"ambush-scarab-of-hidden-compartments"},{"id":"ambush-scarab-of-potency","name":"Ambush Scarab of Potency","image":"/gen/image/WzI1LDE0LHsiZiI6IjJESXRlbXMvQ3VycmVuY3kvU2NhcmFicy9HcmVhdGVyU2NhcmFiU3Ryb25nYm94ZXMiLCJzY2FsZSI6MX1d/c2cb4efc18/GreaterScarabStrongboxes.png","category":"Fragments","detailsId":"ambush-scarab-of-potency"},{"id":"anarchy-scarab-of-gigantification","name":"Anarchy Scarab of Gigantification","image":"/gen/image/WzI1LDE0LHsiZiI6IjJESXRlbXMvQ3VycmVuY3kvU2NhcmFicy9Ob3JtYWxTY2FyYWJBbmFyY2h5Iiwic2NhbGUiOjF9XQ/d391e90e68/NormalScarabAnarchy.png","category":"Fragments","detailsId":"anarchy-scarab-of-gigantification"},{"id":"anarchy-scarab-of-partnership","name":"Anarchy Scarab of Partnership","image":"/gen/image/WzI1LDE0LHsiZiI6IjJESXRlbXMvQ3VycmVuY3kvU2NhcmFicy9HcmVhdGVyU2NhcmFiQW5hcmNoeSIsInNjYWxlIjoxfV0/4697e57871/GreaterScarabAnarchy.png","category":"Fragments","detailsId":"anarchy-scarab-of-partnership"},{"id":"betrayal-scarab-of-perpetuation","name":"Betrayal Scarab of Unbreaking","image":"/gen/image/WzI1LDE0LHsiZiI6IjJESXRlbXMvQ3VycmVuY3kvU2NhcmFicy9UaWVyNFNjYXJhYkJldHJheWFsIiwic2NhbGUiOjF9XQ/4290457e94/Tier4ScarabBetrayal.png","category":"Fragments","detailsId":"betrayal-scarab-of-unbreaking"},{"id":"betrayal-scarab-of-the-allflame","name":"Betrayal Scarab of the Allflame","image":"/gen/image/WzI1LDE0LHsiZiI6IjJESXRlbXMvQ3VycmVuY3kvU2NhcmFicy9Ob3JtYWxTY2FyYWJCZXRyYXlhbCIsInNjYWxlIjoxfV0/3e4a843098/NormalScarabBetrayal.png","category":"Fragments","detailsId":"betrayal-scarab-of-the-allflame"},{"id":"beyond-scarab","name":"Beyond Scarab","image":"/gen/image/WzI1LDE0LHsiZiI6IjJESXRlbXMvQ3VycmVuY3kvU2NhcmFicy9MZXNzZXJTY2FyYWJCZXlvbmQiLCJzY2FsZSI6MX1d/28f0c03cf7/LesserScarabBeyond.png","category":"Fragments","detailsId":"beyond-scarab"},{"id":"beyond-scarab-of-resurgence","name":"Beyond Scarab of Resurgence","image":"/gen/image/WzI1LDE0LHsiZiI6IjJESXRlbXMvQ3VycmVuY3kvU2NhcmFicy9BbHRHcmVhdGVyU2NhcmFiQmV5b25kIiwic2NhbGUiOjF9XQ/4e3cafe44b/AltGreaterScarabBeyond.png","category":"Fragments","detailsId":"beyond-scarab-of-resurgence"},{"id":"blight-scarab","name":"Blight Scarab","image":"/gen/image/WzI1LDE0LHsiZiI6IjJESXRlbXMvQ3VycmVuY3kvU2NhcmFicy9MZXNzZXJTY2FyYWJCbGlnaHQiLCJzY2FsZSI6MX1d/401222e4f4/LesserScarabBlight.png","category":"Fragments","detailsId":"blight-scarab"},{"id":"blight-scarab-of-invigoration","name":"Blight Scarab of Invigoration","image":"/gen/image/WzI1LDE0LHsiZiI6IjJESXRlbXMvQ3VycmVuY3kvU2NhcmFicy9BbHRUaWVyNFNjYXJhYkJsaWdodCIsInNjYWxlIjoxfV0/34e07da01c/AltTier4ScarabBlight.png","category":"Fragments","detailsId":"blight-scarab-of-invigoration"},{"id":"blight-scarab-of-the-blightheart","name":"Blight Scarab of the Blightheart","image":"/gen/image/WzI1LDE0LHsiZiI6IjJESXRlbXMvQ3VycmVuY3kvU2NhcmFicy9HcmVhdGVyU2NhcmFiQmxpZ2h0Iiwic2NhbGUiOjF9XQ/d0aa6a6d55/GreaterScarabBlight.png","category":"Fragments","detailsId":"blight-scarab-of-the-blightheart"},{"id":"breach-scarab-of-lordship","name":"Breach Scarab of Instability","image":"/gen/image/WzI1LDE0LHsiZiI6IjJESXRlbXMvQ3VycmVuY3kvU2NhcmFicy9BbHRMZXNzZXJTY2FyYWJCcmVhY2giLCJzY2FsZSI6MX1d/91af1cf6e9/AltLesserScarabBreach.png","category":"Fragments","detailsId":"breach-scarab-of-instability"},{"id":"breach-scarab-of-splintering","name":"Breach Scarab of the Marshal","image":"/gen/image/WzI1LDE0LHsiZiI6IjJESXRlbXMvQ3VycmVuY3kvU2NhcmFicy9BbHROb3JtYWxTY2FyYWJCcmVhY2giLCJzY2FsZSI6MX1d/864e785561/AltNormalScarabBreach.png","category":"Fragments","detailsId":"breach-scarab-of-the-marshal"},{"id":"cartography-scarab-of-escalation","name":"Cartography Scarab of Escalation","image":"/gen/image/WzI1LDE0LHsiZiI6IjJESXRlbXMvQ3VycmVuY3kvU2NhcmFicy9MZXNzZXJTY2FyYWJNYXBzIiwic2NhbGUiOjF9XQ/e7d11bcc5b/LesserScarabMaps.png","category":"Fragments","detailsId":"cartography-scarab-of-escalation"},{"id":"abyss-scarab","name":"Abyss Scarab","image":"/gen/image/WzI1LDE0LHsiZiI6IjJESXRlbXMvQ3VycmVuY3kvU2NhcmFicy9MZXNzZXJTY2FyYWJBYnlzcyIsInNjYWxlIjoxfV0/05f3ac3c5c/LesserScarabAbyss.png","category":"Fragments","detailsId":"abyss-scarab"},{"id":"abyss-scarab-of-edifice","name":"Abyss Scarab of Edifice","image":"/gen/image/WzI1LDE0LHsiZiI6IjJESXRlbXMvQ3VycmVuY3kvU2NhcmFicy9HcmVhdGVyU2NhcmFiQWJ5c3MiLCJzY2FsZSI6MX1d/84851bd122/GreaterScarabAbyss.png","category":"Fragments","detailsId":"abyss-scarab-of-edifice"},{"id":"abyss-scarab-of-multitudes","name":"Abyss Scarab of Multitudes","image":"/gen/image/WzI1LDE0LHsiZiI6IjJESXRlbXMvQ3VycmVuY3kvU2NhcmFicy9Ob3JtYWxTY2FyYWJBYnlzcyIsInNjYWxlIjoxfV0/e28a53e1a0/NormalScarabAbyss.png","category":"Fragments","detailsId":"abyss-scarab-of-multitudes"},{"id":"anarchy-scarab","name":"Anarchy Scarab","image":"/gen/image/WzI1LDE0LHsiZiI6IjJESXRlbXMvQ3VycmVuY3kvU2NhcmFicy9MZXNzZXJTY2FyYWJBbmFyY2h5Iiwic2NhbGUiOjF9XQ/73d1ee9b23/LesserScarabAnarchy.png","category":"Fragments","detailsId":"anarchy-scarab"},{"id":"anarchy-scarab-of-the-exceptional","name":"Anarchy Scarab of the Exceptional","image":"/gen/image/WzI1LDE0LHsiZiI6IjJESXRlbXMvQ3VycmVuY3kvU2NhcmFicy9UaWVyNFNjYXJhYkFuYXJjaHkiLCJzY2FsZSI6MX1d/3f5f6a8671/Tier4ScarabAnarchy.png","category":"Fragments","detailsId":"anarchy-scarab-of-the-exceptional"},{"id":"bestiary-scarab","name":"Bestiary Scarab","image":"/gen/image/WzI1LDE0LHsiZiI6IjJESXRlbXMvQ3VycmVuY3kvU2NhcmFicy9MZXNzZXJTY2FyYWJCZWFzdHMiLCJzY2FsZSI6MX1d/a13711c8ed/LesserScarabBeasts.png","category":"Fragments","detailsId":"bestiary-scarab"},{"id":"bestiary-scarab-of-duplicating","name":"Bestiary Scarab of Duplicating","image":"/gen/image/WzI1LDE0LHsiZiI6IjJESXRlbXMvQ3VycmVuY3kvU2NhcmFicy9HcmVhdGVyU2NhcmFiQmVhc3RzIiwic2NhbGUiOjF9XQ/09caa391c6/GreaterScarabBeasts.png","category":"Fragments","detailsId":"bestiary-scarab-of-duplicating"},{"id":"bestiary-scarab-of-the-herd","name":"Bestiary Scarab of the Herd","image":"/gen/image/WzI1LDE0LHsiZiI6IjJESXRlbXMvQ3VycmVuY3kvU2NhcmFicy9Ob3JtYWxTY2FyYWJCZWFzdHMiLCJzY2FsZSI6MX1d/0d5c9d2d30/NormalScarabBeasts.png","category":"Fragments","detailsId":"bestiary-scarab-of-the-herd"},{"id":"betrayal-scarab","name":"Betrayal Scarab","image":"/gen/image/WzI1LDE0LHsiZiI6IjJESXRlbXMvQ3VycmVuY3kvU2NhcmFicy9MZXNzZXJTY2FyYWJCZXRyYXlhbCIsInNjYWxlIjoxfV0/d53970be47/LesserScarabBetrayal.png","category":"Fragments","detailsId":"betrayal-scarab"},{"id":"betrayal-scarab-of-reinforcements","name":"Betrayal Scarab of Reinforcements","image":"/gen/image/WzI1LDE0LHsiZiI6IjJESXRlbXMvQ3VycmVuY3kvU2NhcmFicy9HcmVhdGVyU2NhcmFiQmV0cmF5YWwiLCJzY2FsZSI6MX1d/7dd831f857/GreaterScarabBetrayal.png","category":"Fragments","detailsId":"betrayal-scarab-of-reinforcements"},{"id":"beyond-scarab-of-haemophilia","name":"Beyond Scarab of Haemophilia","image":"/gen/image/WzI1LDE0LHsiZiI6IjJESXRlbXMvQ3VycmVuY3kvU2NhcmFicy9Ob3JtYWxTY2FyYWJCZXlvbmQiLCJzY2FsZSI6MX1d/6d3487e108/NormalScarabBeyond.png","category":"Fragments","detailsId":"beyond-scarab-of-haemophilia"},{"id":"beyond-scarab-of-the-invasion","name":"Beyond Scarab of the Invasion","image":"/gen/image/WzI1LDE0LHsiZiI6IjJESXRlbXMvQ3VycmVuY3kvU2NhcmFicy9UaWVyNFNjYXJhYkJleW9uZCIsInNjYWxlIjoxfV0/a1d0b3e27b/Tier4ScarabBeyond.png","category":"Fragments","detailsId":"beyond-scarab-of-the-invasion"},{"id":"blight-scarab-of-blooming","name":"Blight Scarab of Blooming","image":"/gen/image/WzI1LDE0LHsiZiI6IjJESXRlbXMvQ3VycmVuY3kvU2NhcmFicy9UaWVyNFNjYXJhYkJsaWdodCIsInNjYWxlIjoxfV0/7ecd3dcebc/Tier4ScarabBlight.png","category":"Fragments","detailsId":"blight-scarab-of-blooming"},{"id":"breach-scarab","name":"Breach Scarab of the Hive","image":"/gen/image/WzI1LDE0LHsiZiI6IjJESXRlbXMvQ3VycmVuY3kvU2NhcmFicy9MZXNzZXJTY2FyYWJCcmVhY2giLCJzY2FsZSI6MX1d/769139d13b/LesserScarabBreach.png","category":"Fragments","detailsId":"breach-scarab-of-the-hive"},{"id":"breach-scarab-of-resonant-cascade","name":"Breach Scarab of Resonant Cascade","image":"/gen/image/WzI1LDE0LHsiZiI6IjJESXRlbXMvQ3VycmVuY3kvU2NhcmFicy9BbHRUaWVyNFNjYXJhYkJyZWFjaCIsInNjYWxlIjoxfV0/d6fe5cdce6/AltTier4ScarabBreach.png","category":"Fragments","detailsId":"breach-scarab-of-resonant-cascade"},{"id":"breach-scarab-of-snares","name":"Breach Scarab of the Incensed Swarm","image":"/gen/image/WzI1LDE0LHsiZiI6IjJESXRlbXMvQ3VycmVuY3kvU2NhcmFicy9UaWVyNFNjYXJhYkJyZWFjaCIsInNjYWxlIjoxfV0/2e4da41035/Tier4ScarabBreach.png","category":"Fragments","detailsId":"breach-scarab-of-the-incensed-swarm"},{"id":"cartography-scarab-of-corruption","name":"Cartography Scarab of Corruption","image":"/gen/image/WzI1LDE0LHsiZiI6IjJESXRlbXMvQ3VycmVuY3kvU2NhcmFicy9HcmVhdGVyU2NhcmFiTWFwcyIsInNjYWxlIjoxfV0/7c589dbe02/GreaterScarabMaps.png","category":"Fragments","detailsId":"cartography-scarab-of-corruption"},{"id":"cartography-scarab-of-risk","name":"Cartography Scarab of Risk","image":"/gen/image/WzI1LDE0LHsiZiI6IjJESXRlbXMvQ3VycmVuY3kvU2NhcmFicy9Ob3JtYWxTY2FyYWJNYXBzIiwic2NhbGUiOjF9XQ/b41df1ff07/NormalScarabMaps.png","category":"Fragments","detailsId":"cartography-scarab-of-risk"},{"id":"cartography-scarab-of-the-multitude","name":"Cartography Scarab of the Multitude","image":"/gen/image/WzI1LDE0LHsiZiI6IjJESXRlbXMvQ3VycmVuY3kvU2NhcmFicy9BbHROb3JtYWxTY2FyYWJNYXBzIiwic2NhbGUiOjF9XQ/41c689bbef/AltNormalScarabMaps.png","category":"Fragments","detailsId":"cartography-scarab-of-the-multitude"},{"id":"delirium-scarab-of-delusions","name":"Delirium Scarab of Delusions","image":"/gen/image/WzI1LDE0LHsiZiI6IjJESXRlbXMvQ3VycmVuY3kvU2NhcmFicy9UaWVyNFNjYXJhYkRlbGlyaXVtIiwic2NhbGUiOjF9XQ/aa8241bb6c/Tier4ScarabDelirium.png","category":"Fragments","detailsId":"delirium-scarab-of-delusions"},{"id":"delirium-scarab-of-paranoia","name":"Delirium Scarab of Paranoia","image":"/gen/image/WzI1LDE0LHsiZiI6IjJESXRlbXMvQ3VycmVuY3kvU2NhcmFicy9HcmVhdGVyU2NhcmFiRGVsaXJpdW0iLCJzY2FsZSI6MX1d/e6730494ae/GreaterScarabDelirium.png","category":"Fragments","detailsId":"delirium-scarab-of-paranoia"},{"id":"divination-scarab-of-the-cloister","name":"Divination Scarab of The Cloister","image":"/gen/image/WzI1LDE0LHsiZiI6IjJESXRlbXMvQ3VycmVuY3kvU2NhcmFicy9MZXNzZXJTY2FyYWJEaXZpbmF0aW9uIiwic2NhbGUiOjF9XQ/20ff060a8d/LesserScarabDivination.png","category":"Fragments","detailsId":"divination-scarab-of-the-cloister"},{"id":"domination-scarab","name":"Domination Scarab","image":"/gen/image/WzI1LDE0LHsiZiI6IjJESXRlbXMvQ3VycmVuY3kvU2NhcmFicy9MZXNzZXJTY2FyYWJEb21pbmF0aW9uIiwic2NhbGUiOjF9XQ/76cedf832c/LesserScarabDomination.png","category":"Fragments","detailsId":"domination-scarab"},{"id":"domination-scarab-of-apparitions","name":"Domination Scarab of Apparitions","image":"/gen/image/WzI1LDE0LHsiZiI6IjJESXRlbXMvQ3VycmVuY3kvU2NhcmFicy9Ob3JtYWxTY2FyYWJEb21pbmF0aW9uIiwic2NhbGUiOjF9XQ/c907d44dec/NormalScarabDomination.png","category":"Fragments","detailsId":"domination-scarab-of-apparitions"},{"id":"essence-scarab","name":"Essence Scarab","image":"/gen/image/WzI1LDE0LHsiZiI6IjJESXRlbXMvQ3VycmVuY3kvU2NhcmFicy9MZXNzZXJTY2FyYWJFc3NlbmNlIiwic2NhbGUiOjF9XQ/4c99af0610/LesserScarabEssence.png","category":"Fragments","detailsId":"essence-scarab"},{"id":"essence-scarab-of-adaptation","name":"Essence Scarab of Adaptation","image":"/gen/image/WzI1LDE0LHsiZiI6IjJESXRlbXMvQ3VycmVuY3kvU2NhcmFicy9BbHRUaWVyNFNjYXJhYkVzc2VuY2UiLCJzY2FsZSI6MX1d/56560d691e/AltTier4ScarabEssence.png","category":"Fragments","detailsId":"essence-scarab-of-adaptation"},{"id":"essence-scarab-of-ascent","name":"Essence Scarab of Ascent","image":"/gen/image/WzI1LDE0LHsiZiI6IjJESXRlbXMvQ3VycmVuY3kvU2NhcmFicy9Ob3JtYWxTY2FyYWJFc3NlbmNlIiwic2NhbGUiOjF9XQ/3a091b8052/NormalScarabEssence.png","category":"Fragments","detailsId":"essence-scarab-of-ascent"},{"id":"expedition-scarab","name":"Expedition Scarab","image":"/gen/image/WzI1LDE0LHsiZiI6IjJESXRlbXMvQ3VycmVuY3kvU2NhcmFicy9MZXNzZXJTY2FyYWJFeHBlZGl0aW9uIiwic2NhbGUiOjF9XQ/fa49f53ac8/LesserScarabExpedition.png","category":"Fragments","detailsId":"expedition-scarab"},{"id":"expedition-scarab-of-archaeology","name":"Expedition Scarab of Archaeology","image":"/gen/image/WzI1LDE0LHsiZiI6IjJESXRlbXMvQ3VycmVuY3kvU2NhcmFicy9UaWVyNFNjYXJhYkV4cGVkaXRpb24iLCJzY2FsZSI6MX1d/6bd03eec75/Tier4ScarabExpedition.png","category":"Fragments","detailsId":"expedition-scarab-of-archaeology"},{"id":"harvest-scarab","name":"Harvest Scarab","image":"/gen/image/WzI1LDE0LHsiZiI6IjJESXRlbXMvQ3VycmVuY3kvU2NhcmFicy9MZXNzZXJTY2FyYWJIYXJ2ZXN0Iiwic2NhbGUiOjF9XQ/976dcf6526/LesserScarabHarvest.png","category":"Fragments","detailsId":"harvest-scarab"},{"id":"harvest-scarab-of-doubling","name":"Harvest Scarab of Doubling","image":"/gen/image/WzI1LDE0LHsiZiI6IjJESXRlbXMvQ3VycmVuY3kvU2NhcmFicy9HcmVhdGVyU2NhcmFiSGFydmVzdCIsInNjYWxlIjoxfV0/6077972903/GreaterScarabHarvest.png","category":"Fragments","detailsId":"harvest-scarab-of-doubling"},{"id":"horned-scarab-of-awakening","name":"Horned Scarab of Awakening","image":"/gen/image/WzI1LDE0LHsiZiI6IjJESXRlbXMvQ3VycmVuY3kvU2NhcmFicy9TdXBlclNjYXJhYjQiLCJzY2FsZSI6MX1d/c939905663/SuperScarab4.png","category":"Fragments","detailsId":"horned-scarab-of-awakening"},{"id":"horned-scarab-of-bloodlines","name":"Horned Scarab of Bloodlines","image":"/gen/image/WzI1LDE0LHsiZiI6IjJESXRlbXMvQ3VycmVuY3kvU2NhcmFicy9TdXBlclNjYXJhYjEiLCJzY2FsZSI6MX1d/acc1b258a3/SuperScarab1.png","category":"Fragments","detailsId":"horned-scarab-of-bloodlines"},{"id":"horned-scarab-of-glittering","name":"Horned Scarab of Glittering","image":"/gen/image/WzI1LDE0LHsiZiI6IjJESXRlbXMvQ3VycmVuY3kvU2NhcmFicy9TdXBlclNjYXJhYjYiLCJzY2FsZSI6MX1d/f74c2fdd4f/SuperScarab6.png","category":"Fragments","detailsId":"horned-scarab-of-glittering"},{"id":"horned-scarab-of-nemeses","name":"Horned Scarab of Nemeses","image":"/gen/image/WzI1LDE0LHsiZiI6IjJESXRlbXMvQ3VycmVuY3kvU2NhcmFicy9TdXBlclNjYXJhYjIiLCJzY2FsZSI6MX1d/c4f92c444d/SuperScarab2.png","category":"Fragments","detailsId":"horned-scarab-of-nemeses"},{"id":"horned-scarab-of-pandemonium","name":"Horned Scarab of Pandemonium","image":"/gen/image/WzI1LDE0LHsiZiI6IjJESXRlbXMvQ3VycmVuY3kvU2NhcmFicy9TdXBlclNjYXJhYjciLCJzY2FsZSI6MX1d/28b95bae7b/SuperScarab7.png","category":"Fragments","detailsId":"horned-scarab-of-pandemonium"},{"id":"horned-scarab-of-preservation","name":"Horned Scarab of Preservation","image":"/gen/image/WzI1LDE0LHsiZiI6IjJESXRlbXMvQ3VycmVuY3kvU2NhcmFicy9TdXBlclNjYXJhYjMiLCJzY2FsZSI6MX1d/64d9f06e78/SuperScarab3.png","category":"Fragments","detailsId":"horned-scarab-of-preservation"},{"id":"incursion-scarab","name":"Incursion Scarab","image":"/gen/image/WzI1LDE0LHsiZiI6IjJESXRlbXMvQ3VycmVuY3kvU2NhcmFicy9MZXNzZXJTY2FyYWJJbmN1cnNpb24iLCJzY2FsZSI6MX1d/4afd758a13/LesserScarabIncursion.png","category":"Fragments","detailsId":"incursion-scarab"},{"id":"incursion-scarab-of-champions","name":"Incursion Scarab of Champions","image":"/gen/image/WzI1LDE0LHsiZiI6IjJESXRlbXMvQ3VycmVuY3kvU2NhcmFicy9HcmVhdGVyU2NhcmFiSW5jdXJzaW9uIiwic2NhbGUiOjF9XQ/ff92bda004/GreaterScarabIncursion.png","category":"Fragments","detailsId":"incursion-scarab-of-champions"},{"id":"influencing-scarab-of-hordes","name":"Influencing Scarab of Hordes","image":"/gen/image/WzI1LDE0LHsiZiI6IjJESXRlbXMvQ3VycmVuY3kvU2NhcmFicy9HcmVhdGVyU2NhcmFiRWxkZXIiLCJzY2FsZSI6MX1d/660528eb40/GreaterScarabElder.png","category":"Fragments","detailsId":"influencing-scarab-of-hordes"},{"id":"influencing-scarab-of-the-elder","name":"Influencing Scarab of the Elder","image":"/gen/image/WzI1LDE0LHsiZiI6IjJESXRlbXMvQ3VycmVuY3kvU2NhcmFicy9MZXNzZXJTY2FyYWJFbGRlciIsInNjYWxlIjoxfV0/8828d3f4eb/LesserScarabElder.png","category":"Fragments","detailsId":"influencing-scarab-of-the-elder"},{"id":"influencing-scarab-of-the-shaper","name":"Influencing Scarab of the Shaper","image":"/gen/image/WzI1LDE0LHsiZiI6IjJESXRlbXMvQ3VycmVuY3kvU2NhcmFicy9MZXNzZXJTY2FyYWJTaGFwZXIiLCJzY2FsZSI6MX1d/caf0ac9307/LesserScarabShaper.png","category":"Fragments","detailsId":"influencing-scarab-of-the-shaper"},{"id":"kalguuran-scarab","name":"Kalguuran Scarab","image":"/gen/image/WzI1LDE0LHsiZiI6IjJESXRlbXMvQ3VycmVuY3kvU2NhcmFicy9MZXNzZXJTY2FyYWJTZXR0bGVycyIsInNjYWxlIjoxfV0/591426ae68/LesserScarabSettlers.png","category":"Fragments","detailsId":"kalguuran-scarab"},{"id":"kalguuran-scarab-of-enriching","name":"Kalguuran Scarab of Enriching","image":"/gen/image/WzI1LDE0LHsiZiI6IjJESXRlbXMvQ3VycmVuY3kvU2NhcmFicy9UaWVyNFNjYXJhYlNldHRsZXJzIiwic2NhbGUiOjF9XQ/62d3e05936/Tier4ScarabSettlers.png","category":"Fragments","detailsId":"kalguuran-scarab-of-enriching"},{"id":"kalguuran-scarab-of-guarded-riches","name":"Kalguuran Scarab of Guarded Riches","image":"/gen/image/WzI1LDE0LHsiZiI6IjJESXRlbXMvQ3VycmVuY3kvU2NhcmFicy9Ob3JtYWxTY2FyYWJTZXR0bGVycyIsInNjYWxlIjoxfV0/5ab4be93db/NormalScarabSettlers.png","category":"Fragments","detailsId":"kalguuran-scarab-of-guarded-riches"},{"id":"legion-scarab-of-command","name":"Legion Scarab of Treasures","image":"/gen/image/WzI1LDE0LHsiZiI6IjJESXRlbXMvQ3VycmVuY3kvU2NhcmFicy9BbHROb3JtYWxTY2FyYWJMZWdpb24iLCJzY2FsZSI6MX1d/5d88c1f891/AltNormalScarabLegion.png","category":"Fragments","detailsId":"legion-scarab-of-treasures"},{"id":"legion-scarab-of-officers","name":"Legion Scarab of Officers","image":"/gen/image/WzI1LDE0LHsiZiI6IjJESXRlbXMvQ3VycmVuY3kvU2NhcmFicy9Ob3JtYWxTY2FyYWJMZWdpb24iLCJzY2FsZSI6MX1d/986b842d3f/NormalScarabLegion.png","category":"Fragments","detailsId":"legion-scarab-of-officers"},{"id":"ritual-scarab-of-abundance","name":"Ritual Scarab of Abundance","image":"/gen/image/WzI1LDE0LHsiZiI6IjJESXRlbXMvQ3VycmVuY3kvU2NhcmFicy9HcmVhdGVyU2NhcmFiUml0dWFsIiwic2NhbGUiOjF9XQ/a990c91de5/GreaterScarabRitual.png","category":"Fragments","detailsId":"ritual-scarab-of-abundance"},{"id":"ritual-scarab-of-corpses","name":"Ritual Scarab of Corpses","image":"/gen/image/WzI1LDE0LHsiZiI6IjJESXRlbXMvQ3VycmVuY3kvU2NhcmFicy9UaWVyNFNjYXJhYlJpdHVhbCIsInNjYWxlIjoxfV0/323f689e68/Tier4ScarabRitual.png","category":"Fragments","detailsId":"ritual-scarab-of-corpses"},{"id":"ritual-scarab-of-wisps","name":"Ritual Scarab of Wisps","image":"/gen/image/WzI1LDE0LHsiZiI6IjJESXRlbXMvQ3VycmVuY3kvU2NhcmFicy9Ob3JtYWxTY2FyYWJSaXR1YWwiLCJzY2FsZSI6MX1d/f2c3231213/NormalScarabRitual.png","category":"Fragments","detailsId":"ritual-scarab-of-wisps"},{"id":"scarab-of-divinity","name":"Scarab of Divinity","image":"/gen/image/WzI1LDE0LHsiZiI6IjJESXRlbXMvQ3VycmVuY3kvU2NhcmFicy9Ob3JtYWxTY2FyYWJNaXNjIiwic2NhbGUiOjF9XQ/6d4755a692/NormalScarabMisc.png","category":"Fragments","detailsId":"scarab-of-divinity"},{"id":"scarab-of-monstrous-lineage","name":"Scarab of Monstrous Lineage","image":"/gen/image/WzI1LDE0LHsiZiI6IjJESXRlbXMvQ3VycmVuY3kvU2NhcmFicy9MZXNzZXJTY2FyYWJNaXNjIiwic2NhbGUiOjF9XQ/9196715e8d/LesserScarabMisc.png","category":"Fragments","detailsId":"scarab-of-monstrous-lineage"},{"id":"scarab-of-wisps","name":"Scarab of Wisps","image":"/gen/image/WzI1LDE0LHsiZiI6IjJESXRlbXMvQ3VycmVuY3kvU2NhcmFicy9HcmVhdGVyU2NhcmFiTWlzYzEiLCJzY2FsZSI6MX1d/303001a475/GreaterScarabMisc1.png","category":"Fragments","detailsId":"scarab-of-wisps"},{"id":"sulphite-scarab","name":"Sulphite Scarab","image":"/gen/image/WzI1LDE0LHsiZiI6IjJESXRlbXMvQ3VycmVuY3kvU2NhcmFicy9MZXNzZXJTY2FyYWJTdWxwaGl0ZSIsInNjYWxlIjoxfV0/9bdde2cec0/LesserScarabSulphite.png","category":"Fragments","detailsId":"sulphite-scarab"},{"id":"sulphite-scarab-of-fumes","name":"Sulphite Scarab of Fumes","image":"/gen/image/WzI1LDE0LHsiZiI6IjJESXRlbXMvQ3VycmVuY3kvU2NhcmFicy9HcmVhdGVyU2NhcmFiU3VscGhpdGUiLCJzY2FsZSI6MX1d/55c0fed4b6/GreaterScarabSulphite.png","category":"Fragments","detailsId":"sulphite-scarab-of-fumes"},{"id":"torment-scarab-of-peculiarity","name":"Torment Scarab of Peculiarity","image":"/gen/image/WzI1LDE0LHsiZiI6IjJESXRlbXMvQ3VycmVuY3kvU2NhcmFicy9Ob3JtYWxTY2FyYWJUb3JtZW50Iiwic2NhbGUiOjF9XQ/4c94a84fd8/NormalScarabTorment.png","category":"Fragments","detailsId":"torment-scarab-of-peculiarity"},{"id":"ultimatum-scarab-of-catalysing","name":"Ultimatum Scarab of Catalysing","image":"/gen/image/WzI1LDE0LHsiZiI6IjJESXRlbXMvQ3VycmVuY3kvU2NhcmFicy9UaWVyNFNjYXJhYlVsdGltYXR1bSIsInNjYWxlIjoxfV0/abfc80cf45/Tier4ScarabUltimatum.png","category":"Fragments","detailsId":"ultimatum-scarab-of-catalysing"},{"id":"ultimatum-scarab-of-inscription","name":"Ultimatum Scarab of Inscription","image":"/gen/image/WzI1LDE0LHsiZiI6IjJESXRlbXMvQ3VycmVuY3kvU2NhcmFicy9BbHRUaWVyNFNjYXJhYlVsdGltYXR1bSIsInNjYWxlIjoxfV0/080e60e969/AltTier4ScarabUltimatum.png","category":"Fragments","detailsId":"ultimatum-scarab-of-inscription"},{"id":"delirium-scarab","name":"Delirium Scarab","image":"/gen/image/WzI1LDE0LHsiZiI6IjJESXRlbXMvQ3VycmVuY3kvU2NhcmFicy9MZXNzZXJTY2FyYWJEZWxpcml1bSIsInNjYWxlIjoxfV0/0b8b887e88/LesserScarabDelirium.png","category":"Fragments","detailsId":"delirium-scarab"},{"id":"delirium-scarab-of-mania","name":"Delirium Scarab of Mania","image":"/gen/image/WzI1LDE0LHsiZiI6IjJESXRlbXMvQ3VycmVuY3kvU2NhcmFicy9Ob3JtYWxTY2FyYWJEZWxpcml1bSIsInNjYWxlIjoxfV0/9de6ce65c5/NormalScarabDelirium.png","category":"Fragments","detailsId":"delirium-scarab-of-mania"},{"id":"delirium-scarab-of-neuroses","name":"Delirium Scarab of Neuroses","image":"/gen/image/WzI1LDE0LHsiZiI6IjJESXRlbXMvQ3VycmVuY3kvU2NhcmFicy9BbHRHcmVhdGVyU2NhcmFiRGVsaXJpdW0iLCJzY2FsZSI6MX1d/5690762715/AltGreaterScarabDelirium.png","category":"Fragments","detailsId":"delirium-scarab-of-neuroses"},{"id":"divination-scarab-of-pilfering","name":"Divination Scarab of Pilfering","image":"/gen/image/WzI1LDE0LHsiZiI6IjJESXRlbXMvQ3VycmVuY3kvU2NhcmFicy9HcmVhdGVyU2NhcmFiRGl2aW5hdGlvbiIsInNjYWxlIjoxfV0/73ab11f6bd/GreaterScarabDivination.png","category":"Fragments","detailsId":"divination-scarab-of-pilfering"},{"id":"divination-scarab-of-plenty","name":"Divination Scarab of Plenty","image":"/gen/image/WzI1LDE0LHsiZiI6IjJESXRlbXMvQ3VycmVuY3kvU2NhcmFicy9Ob3JtYWxTY2FyYWJEaXZpbmF0aW9uIiwic2NhbGUiOjF9XQ/acb5d1754a/NormalScarabDivination.png","category":"Fragments","detailsId":"divination-scarab-of-plenty"},{"id":"domination-scarab-of-evolution","name":"Domination Scarab of Evolution","image":"/gen/image/WzI1LDE0LHsiZiI6IjJESXRlbXMvQ3VycmVuY3kvU2NhcmFicy9HcmVhdGVyU2NhcmFiRG9taW5hdGlvbiIsInNjYWxlIjoxfV0/8913234164/GreaterScarabDomination.png","category":"Fragments","detailsId":"domination-scarab-of-evolution"},{"id":"domination-scarab-of-terrors","name":"Domination Scarab of Terrors","image":"/gen/image/WzI1LDE0LHsiZiI6IjJESXRlbXMvQ3VycmVuY3kvU2NhcmFicy9UaWVyNFNjYXJhYkRvbWluYXRpb24iLCJzY2FsZSI6MX1d/0d55e72414/Tier4ScarabDomination.png","category":"Fragments","detailsId":"domination-scarab-of-terrors"},{"id":"essence-scarab-of-calcification","name":"Essence Scarab of Calcification","image":"/gen/image/WzI1LDE0LHsiZiI6IjJESXRlbXMvQ3VycmVuY3kvU2NhcmFicy9UaWVyNFNjYXJhYkVzc2VuY2UiLCJzY2FsZSI6MX1d/d7e7534a07/Tier4ScarabEssence.png","category":"Fragments","detailsId":"essence-scarab-of-calcification"},{"id":"essence-scarab-of-stability","name":"Essence Scarab of Stability","image":"/gen/image/WzI1LDE0LHsiZiI6IjJESXRlbXMvQ3VycmVuY3kvU2NhcmFicy9HcmVhdGVyU2NhcmFiRXNzZW5jZSIsInNjYWxlIjoxfV0/28e74041a5/GreaterScarabEssence.png","category":"Fragments","detailsId":"essence-scarab-of-stability"},{"id":"expedition-scarab-of-runefinding","name":"Expedition Scarab of Runefinding","image":"/gen/image/WzI1LDE0LHsiZiI6IjJESXRlbXMvQ3VycmVuY3kvU2NhcmFicy9Ob3JtYWxTY2FyYWJFeHBlZGl0aW9uIiwic2NhbGUiOjF9XQ/a751f91a8e/NormalScarabExpedition.png","category":"Fragments","detailsId":"expedition-scarab-of-runefinding"},{"id":"expedition-scarab-of-the-skald","name":"Expedition Scarab of Infusion","image":"/gen/image/WzI1LDE0LHsiZiI6IjJESXRlbXMvQ3VycmVuY3kvU2NhcmFicy9BbHRHcmVhdGVyU2NhcmFiRXhwZWRpdGlvbiIsInNjYWxlIjoxfV0/cbeb3c974b/AltGreaterScarabExpedition.png","category":"Fragments","detailsId":"expedition-scarab-of-infusion"},{"id":"expedition-scarab-of-verisium-powder","name":"Expedition Scarab of Verisium Powder","image":"/gen/image/WzI1LDE0LHsiZiI6IjJESXRlbXMvQ3VycmVuY3kvU2NhcmFicy9HcmVhdGVyU2NhcmFiRXhwZWRpdGlvbiIsInNjYWxlIjoxfV0/1bf78dd20a/GreaterScarabExpedition.png","category":"Fragments","detailsId":"expedition-scarab-of-verisium-powder"},{"id":"harvest-scarab-of-cornucopia","name":"Harvest Scarab of Cornucopia","image":"/gen/image/WzI1LDE0LHsiZiI6IjJESXRlbXMvQ3VycmVuY3kvU2NhcmFicy9UaWVyNFNjYXJhYkhhcnZlc3QiLCJzY2FsZSI6MX1d/35e8847de2/Tier4ScarabHarvest.png","category":"Fragments","detailsId":"harvest-scarab-of-cornucopia"},{"id":"horned-scarab-of-tradition","name":"Horned Scarab of Tradition","image":"/gen/image/WzI1LDE0LHsiZiI6IjJESXRlbXMvQ3VycmVuY3kvU2NhcmFicy9TdXBlclNjYXJhYjUiLCJzY2FsZSI6MX1d/cbdd57fa7e/SuperScarab5.png","category":"Fragments","detailsId":"horned-scarab-of-tradition"},{"id":"incursion-scarab-of-invasion","name":"Incursion Scarab of Invasion","image":"/gen/image/WzI1LDE0LHsiZiI6IjJESXRlbXMvQ3VycmVuY3kvU2NhcmFicy9Ob3JtYWxTY2FyYWJJbmN1cnNpb24iLCJzY2FsZSI6MX1d/a38b517f35/NormalScarabIncursion.png","category":"Fragments","detailsId":"incursion-scarab-of-invasion"},{"id":"incursion-scarab-of-timelines","name":"Incursion Scarab of Timelines","image":"/gen/image/WzI1LDE0LHsiZiI6IjJESXRlbXMvQ3VycmVuY3kvU2NhcmFicy9UaWVyNFNjYXJhYkluY3Vyc2lvbiIsInNjYWxlIjoxfV0/748b10e2cf/Tier4ScarabIncursion.png","category":"Fragments","detailsId":"incursion-scarab-of-timelines"},{"id":"influencing-scarab-of-conversion","name":"Influencing Scarab of Interference","image":"/gen/image/WzI1LDE0LHsiZiI6IjJESXRlbXMvQ3VycmVuY3kvU2NhcmFicy9UaWVyNFNjYXJhYlNoYXBlciIsInNjYWxlIjoxfV0/320c05daeb/Tier4ScarabShaper.png","category":"Fragments","detailsId":"influencing-scarab-of-interference"},{"id":"kalguuran-scarab-of-refinement","name":"Kalguuran Scarab of Refinement","image":"/gen/image/WzI1LDE0LHsiZiI6IjJESXRlbXMvQ3VycmVuY3kvU2NhcmFicy9HcmVhdGVyU2NhcmFiU2V0dGxlcnMiLCJzY2FsZSI6MX1d/24f57aa157/GreaterScarabSettlers.png","category":"Fragments","detailsId":"kalguuran-scarab-of-refinement"},{"id":"legion-scarab","name":"Legion Scarab","image":"/gen/image/WzI1LDE0LHsiZiI6IjJESXRlbXMvQ3VycmVuY3kvU2NhcmFicy9MZXNzZXJTY2FyYWJMZWdpb24iLCJzY2FsZSI6MX1d/e7b6e5659c/LesserScarabLegion.png","category":"Fragments","detailsId":"legion-scarab"},{"id":"legion-scarab-of-eternal-conflict","name":"Legion Scarab of Eternal Conflict","image":"/gen/image/WzI1LDE0LHsiZiI6IjJESXRlbXMvQ3VycmVuY3kvU2NhcmFicy9UaWVyNFNjYXJhYkxlZ2lvbiIsInNjYWxlIjoxfV0/4a56211137/Tier4ScarabLegion.png","category":"Fragments","detailsId":"legion-scarab-of-eternal-conflict"},{"id":"ritual-scarab-of-selectiveness","name":"Ritual Scarab of Selectiveness","image":"/gen/image/WzI1LDE0LHsiZiI6IjJESXRlbXMvQ3VycmVuY3kvU2NhcmFicy9MZXNzZXJTY2FyYWJSaXR1YWwiLCJzY2FsZSI6MX1d/08f82dab28/LesserScarabRitual.png","category":"Fragments","detailsId":"ritual-scarab-of-selectiveness"},{"id":"scarab-of-adversaries","name":"Scarab of Adversaries","image":"/gen/image/WzI1LDE0LHsiZiI6IjJESXRlbXMvQ3VycmVuY3kvU2NhcmFicy9BbHRMZXNzZXJTY2FyYWJNaXNjIiwic2NhbGUiOjF9XQ/ab24a34cd1/AltLesserScarabMisc.png","category":"Fragments","detailsId":"scarab-of-adversaries"},{"id":"scarab-of-radiant-storms","name":"Scarab of Radiant Storms","image":"/gen/image/WzI1LDE0LHsiZiI6IjJESXRlbXMvQ3VycmVuY3kvU2NhcmFicy9UaWVyNFNjYXJhYk1pc2MyIiwic2NhbGUiOjF9XQ/d19b59b6b8/Tier4ScarabMisc2.png","category":"Fragments","detailsId":"scarab-of-radiant-storms"},{"id":"scarab-of-stability","name":"Scarab of Stability","image":"/gen/image/WzI1LDE0LHsiZiI6IjJESXRlbXMvQ3VycmVuY3kvU2NhcmFicy9UaWVyNFNjYXJhYk1pc2MiLCJzY2FsZSI6MX1d/c80f553284/Tier4ScarabMisc.png","category":"Fragments","detailsId":"scarab-of-stability"},{"id":"scarab-of-the-dextral","name":"Scarab of the Dextral","image":"/gen/image/WzI1LDE0LHsiZiI6IjJESXRlbXMvQ3VycmVuY3kvU2NhcmFicy9BbHRHcmVhdGVyU2NhcmFiTWlzYyIsInNjYWxlIjoxfV0/4b55da6494/AltGreaterScarabMisc.png","category":"Fragments","detailsId":"scarab-of-the-dextral"},{"id":"scarab-of-the-sinistral","name":"Scarab of the Sinistral","image":"/gen/image/WzI1LDE0LHsiZiI6IjJESXRlbXMvQ3VycmVuY3kvU2NhcmFicy9HcmVhdGVyU2NhcmFiTWlzYzIiLCJzY2FsZSI6MX1d/6f752909bb/GreaterScarabMisc2.png","category":"Fragments","detailsId":"scarab-of-the-sinistral"},{"id":"titanic-scarab","name":"Titanic Scarab","image":"/gen/image/WzI1LDE0LHsiZiI6IjJESXRlbXMvQ3VycmVuY3kvU2NhcmFicy9MZXNzZXJTY2FyYWJVbmlxdWUiLCJzY2FsZSI6MX1d/9ed658ddba/LesserScarabUnique.png","category":"Fragments","detailsId":"titanic-scarab"},{"id":"titanic-scarab-of-legend","name":"Titanic Scarab of Legend","image":"/gen/image/WzI1LDE0LHsiZiI6IjJESXRlbXMvQ3VycmVuY3kvU2NhcmFicy9HcmVhdGVyU2NhcmFiVW5pcXVlIiwic2NhbGUiOjF9XQ/0194f878a0/GreaterScarabUnique.png","category":"Fragments","detailsId":"titanic-scarab-of-legend"},{"id":"titanic-scarab-of-treasures","name":"Titanic Scarab of Treasures","image":"/gen/image/WzI1LDE0LHsiZiI6IjJESXRlbXMvQ3VycmVuY3kvU2NhcmFicy9Ob3JtYWxTY2FyYWJVbmlxdWUiLCJzY2FsZSI6MX1d/e2945f5878/NormalScarabUnique.png","category":"Fragments","detailsId":"titanic-scarab-of-treasures"},{"id":"torment-scarab","name":"Torment Scarab","image":"/gen/image/WzI1LDE0LHsiZiI6IjJESXRlbXMvQ3VycmVuY3kvU2NhcmFicy9MZXNzZXJTY2FyYWJUb3JtZW50Iiwic2NhbGUiOjF9XQ/8c43bf8c64/LesserScarabTorment.png","category":"Fragments","detailsId":"torment-scarab"},{"id":"torment-scarab-of-possession","name":"Torment Scarab of Possession","image":"/gen/image/WzI1LDE0LHsiZiI6IjJESXRlbXMvQ3VycmVuY3kvU2NhcmFicy9UaWVyNFNjYXJhYlRvcm1lbnQiLCJzY2FsZSI6MX1d/5b3bed9d3d/Tier4ScarabTorment.png","category":"Fragments","detailsId":"torment-scarab-of-possession"},{"id":"ultimatum-scarab","name":"Ultimatum Scarab","image":"/gen/image/WzI1LDE0LHsiZiI6IjJESXRlbXMvQ3VycmVuY3kvU2NhcmFicy9MZXNzZXJTY2FyYWJVbHRpbWF0dW0iLCJzY2FsZSI6MX1d/b1b423625d/LesserScarabUltimatum.png","category":"Fragments","detailsId":"ultimatum-scarab"},{"id":"ultimatum-scarab-of-bribing","name":"Ultimatum Scarab of Bribing","image":"/gen/image/WzI1LDE0LHsiZiI6IjJESXRlbXMvQ3VycmVuY3kvU2NhcmFicy9Ob3JtYWxTY2FyYWJVbHRpbWF0dW0iLCJzY2FsZSI6MX1d/d688264f91/NormalScarabUltimatum.png","category":"Fragments","detailsId":"ultimatum-scarab-of-bribing"},{"id":"ultimatum-scarab-of-dueling","name":"Ultimatum Scarab of Dueling","image":"/gen/image/WzI1LDE0LHsiZiI6IjJESXRlbXMvQ3VycmVuY3kvU2NhcmFicy9HcmVhdGVyU2NhcmFiVWx0aW1hdHVtIiwic2NhbGUiOjF9XQ/be3b513bfe/GreaterScarabUltimatum.png","category":"Fragments","detailsId":"ultimatum-scarab-of-dueling"}]}